src/core.sv
module core(
  input clk_i,
  input rst_i,
  // Работа с внешними устройствами
  input irq_i,          // Сигнал прерывания
  input [7:0] io_data_i,// Данные от устройств ввода
  output reg [7:0] io_data_o,// Данные для устройств вывода
  output reg [7:0] io_addr_o,// Адрес устройства ввода/вывода
  output reg io_we_o,   // Сигнал записи в устройство вывода
  // Интерфейс памяти
  output reg [15:0] address_o,  
  input [7:0] data_i,
  output reg we_i,              
  output reg [7:0] data_o
);

  // Состояния конечного автомата
  localparam IDLE_S     = 4'd0;
  localparam FETCH_S    = 4'd1;
  localparam DECODE_S   = 4'd2;
  localparam FETCH2_S   = 4'd3;
  localparam FETCH3_S   = 4'd4;
  localparam EXEC_S     = 4'd5;
  localparam MEM_S      = 4'd6;
  localparam WB_S       = 4'd7;
  localparam HALT_S     = 4'd13; // Состояние останова
  localparam V_S        = 4'd14;
  localparam V2_S = 4'd12;
  localparam INT_SAVE1_S = 4'd8; // Сохранение PC младший байт
  localparam INT_SAVE2_S = 4'd9; // Сохранение PC старший байт
  localparam INT_SAVE3_S = 4'd10; // Сохранение флагов
  localparam INT_JUMP_S = 4'd11;  // Переход к обработчику
  localparam INT_JUMP2_S = 4'd15;

  // Определение битов флагов
  localparam FLAG_Z     = 0; // Zero
  localparam FLAG_C     = 1; // Carry
  localparam FLAG_V     = 2; // Overflow
  localparam FLAG_S     = 3; // Sign
  localparam FLAG_IF    = 4; // Interrupt Flag

  // Адрес вектора прерываний
  localparam IVT_ADDR   = 16'hFFFE;

  // Регистры процессора
  reg [3:0] state;
  reg [7:0] RF [0:3];  // Регистровый файл (A=0, B=1, C=2, D=3)
  reg [15:0] PC;       // Счетчик команд
  reg [15:0] SP;       // Указатель стека
  reg [7:0] flags;     // Регистр флагов
  
  // Регистры для хранения инструкций
  reg [7:0] instruction;
  reg [7:0] instruction_2nd_byte;
  reg [7:0] instruction_3rd_byte;
  
  // Временные регистры
  reg [7:0] alu_result;
  reg [8:0] alu_result_ext; // 9 бит для учета переноса

  reg [15:0] int_save_pc;   
  reg [15:0] int_load_pc; 
  reg [7:0] int_save_flags;   
  reg int_pending;          // Флаг ожидания прерывания
  reg irq_i_past;
  // Комбинационные сигналы
  wire [3:0] opcode = instruction[7:4];
  wire [1:0] reg1 = instruction[3:2];
  wire [1:0] reg2 = instruction[1:0];
  wire [7:0] imm8 = instruction_2nd_byte;
  wire [15:0] addr16 = {instruction_2nd_byte, instruction_3rd_byte};


  always_ff @(posedge clk_i) begin
     irq_i_past <= irq_i;
  end

  // Логика следующего состояния
  always @(posedge clk_i or posedge rst_i) begin
    if (irq_i_past == 1'b0 && irq_i == 1'b1) int_pending <= 1'b1;
    if (rst_i) begin
      state <= IDLE_S;
      PC <= 16'h0000;
      SP <= 16'hFFF0;
      flags <= 8'b00000000;
      we_i <= 1'b0;
      io_we_o <= 1'b0;
      int_pending <= 1'b0;
      irq_i_past <= 1'b0;
      RF[0] <= '0;
      RF[1] <= '0;
      RF[2] <= '0;
      RF[3] <= '0;
    end else begin
      case (state)
        IDLE_S: begin
          if (!halt) state <= FETCH_S;
        end
        
        FETCH_S: begin
          instruction <= data_i;
          state <= DECODE_S;
        end
        
        DECODE_S: begin
          case (opcode)
            // 2-байтовые команды
            4'h7, 4'h8, 4'hB, 4'hC: begin
              PC <= PC + 1;
              state <= V_S;
              
            end
            // 3-байтовые команды
            4'h9, 4'hA, 4'hD: begin
              PC <= PC + 1;
              state <= V_S;
            end
            // 1-байтовые команды
            default: state <= EXEC_S;
          endcase
        end
        
        V_S: state <= FETCH2_S;

        FETCH2_S: begin
          instruction_2nd_byte <= data_i;
          case (opcode)
            // 3-байтовые команды
            4'h9, 4'hA, 4'hD: begin
              PC <= PC + 1;
              state <= V2_S;
            end
            // 2-байтовые команды
            default: state <= EXEC_S;
          endcase
        end
        
        V2_S: state <= FETCH3_S;

        FETCH3_S: begin
          instruction_3rd_byte <= data_i;
          state <= EXEC_S;
        end
        
        EXEC_S: begin
          // Выполнение операции
          case (opcode)
            // MOV R1, R2
            4'h1: alu_result <= RF[reg2];
            
            // ADD R1, R2
            4'h2: alu_result_ext <= RF[reg1] + RF[reg2];
            
            // SUB R1, R2
            4'h3: alu_result_ext <= RF[reg1] - RF[reg2];
            
            // AND R1, R2
            4'h4: alu_result <= RF[reg1] & RF[reg2];
            
            // OR R1, R2
            4'h5: alu_result <= RF[reg1] | RF[reg2];
            
            // XOR R1, R2
            4'h6: alu_result <= RF[reg1] ^ RF[reg2];
            
            // MOV R, IMM8
            4'h7: alu_result <= imm8;
            
            // ADD R, IMM8
            4'h8: alu_result_ext <= RF[reg1] + imm8;
            
            // MOV [ADDR16], R
            4'h9: begin
              address_o <= addr16;
              data_o <= RF[reg2];
              we_i <= 1'b1;
            end
            
            // MOV R, [ADDR16]
            4'hA: begin
              address_o <= addr16;
            end
            
            // IN R, PORT8
            4'hB: begin
              io_addr_o <= imm8;
              io_we_o <= 1'b0;
            end
            
            // OUT PORT8, R
            4'hC: begin
              io_addr_o <= imm8;
              io_data_o <= RF[reg1];
              io_we_o <= 1'b1;
            end
            
            // JMP/JZ/JC ADDR16
            4'hD: begin
              case (instruction[3:0])
                4'd0: PC <= addr16; // JMP
                4'd1: if (flags[FLAG_Z]) PC <= addr16; // JZ
                4'd2: if (flags[FLAG_C]) PC <= addr16; // JC
              endcase
            end
            
            // EI/DI
            4'hE: begin
              case (instruction[3:0])
                4'h1: begin
                  flags <= int_save_flags;
                  PC <= int_save_pc;
                  state <= IDLE_S;
                end
                4'h2: flags[FLAG_IF] <= 1'b1; // EI
                4'h3: flags[FLAG_IF] <= 1'b0; // DI
                4'hF: begin /* HALT - обрабатывается отдельно */ end
              endcase
            end
          endcase
          
          // Переход в следующее состояние
          if (opcode == 4'h9 || opcode == 4'hA || opcode == 4'hB || opcode == 4'hC) begin
            state <= MEM_S;
          end else begin
            state <= WB_S;
          end
        end
        
        MEM_S: begin
          we_i <= 1'b0;
          io_we_o <= 1'b0;
          state <= WB_S;
        end
        
        WB_S: begin
          case (opcode)
            // MOV R1, R2
            4'h1: RF[reg1] <= alu_result;
            
            // ADD R1, R2
            4'h2: begin
              RF[reg1] <= alu_result_ext[7:0];
              flags[FLAG_Z] <= (alu_result_ext[7:0] == 8'b0);
              flags[FLAG_C] <= alu_result_ext[8];
              flags[FLAG_V] <= (RF[reg1][7] == RF[reg2][7]) && 
                              (alu_result_ext[7] != RF[reg1][7]);
              flags[FLAG_S] <= alu_result_ext[7];
            end
            
            // SUB R1, R2
            4'h3: begin
              RF[reg1] <= alu_result_ext[7:0];
              flags[FLAG_Z] <= (alu_result_ext[7:0] == 8'b0);
              flags[FLAG_C] <= alu_result_ext[8];
              flags[FLAG_V] <= (RF[reg1][7] != RF[reg2][7]) && 
                              (alu_result_ext[7] != RF[reg1][7]);
              flags[FLAG_S] <= alu_result_ext[7];
            end
            
            // AND/OR/XOR R1, R2
            4'h4, 4'h5, 4'h6: begin
              RF[reg1] <= alu_result;
              flags[FLAG_Z] <= (alu_result == 8'b0);
              flags[FLAG_S] <= alu_result[7];
              flags[FLAG_C] <= 1'b0;
              flags[FLAG_V] <= 1'b0;
            end
            
            // MOV R, IMM8
            4'h7: RF[reg2] <= alu_result;
            
            // ADD R, IMM8
            4'h8: begin
              RF[reg1] <= alu_result_ext[7:0];
              flags[FLAG_Z] <= (alu_result_ext[7:0] == 8'b0);
              flags[FLAG_C] <= alu_result_ext[8];
              flags[FLAG_V] <= (RF[reg1][7] == imm8[7]) && 
                              (alu_result_ext[7] != RF[reg1][7]);
              flags[FLAG_S] <= alu_result_ext[7];
            end
            
            // MOV R, [ADDR16]
            4'hA: RF[reg2] <= data_i;
            
            // IN R, PORT8
            4'hB: RF[reg1] <= io_data_i;
          endcase
          
          // Обновление PC для всех команд кроме JMP/JZ/JC
          if (opcode != 4'hD) begin
            PC <= PC + 1;
          end
          
          // Проверяем, есть ли ожидающее прерывание
          if (int_pending) begin
            state <= INT_SAVE1_S;
            int_pending <= 1'b0;
          end else begin
            state <= IDLE_S;
          end
        end
        
        // Сохранение младшего байта PC
        INT_SAVE1_S: begin
          int_save_pc <= PC;
          int_save_flags <= flags;
          state <= INT_SAVE2_S;
        end
        
        // Сохранение старшего байта PC
        INT_SAVE2_S: begin
          PC <= data_i;
          state <= INT_SAVE3_S;
        end
        
        // Сохранение флагов
        INT_SAVE3_S: begin
          PC[15:8] <= data_i; // Читаем адрес обработчика
          state <= IDLE_S;
        end
        
        HALT_S: begin
          // Останов процессора
          if (irq_i && flags[FLAG_IF]) begin
            int_pending <= 1'b1;
            state <= INT_SAVE1_S;
          end
        end
      endcase
    end
  end

  // Логика прерываний
  always @(posedge clk_i) begin
    if (rst_i) begin
      int_pending <= 1'b0;
    end else if (irq_i && flags[FLAG_IF] && !halt && !int_pending) begin
      // Запоминаем запрос прерывания, если он разрешен
      int_pending <= 1'b1;
    end else if (state == INT_JUMP_S) begin
      // Сбрасываем флаг после перехода к обработчику
      int_pending <= 1'b0;
    end
  end


  // Останов процессора
  reg halt;
  always @(posedge clk_i) begin
    if (rst_i) begin
      halt <= 1'b0;
    end else if (state == EXEC_S && opcode == 4'hE && instruction[3:0] == 4'hF) begin
      halt <= 1'b1;
      state <= HALT_S;
    end
  end

  // Управление адресом памяти
  always @(*) begin
    case (state)
      V_S, V2_S, FETCH_S, FETCH2_S, FETCH3_S: address_o <= PC;
      EXEC_S: begin
        case (opcode)
          4'h9, 4'hA: address_o <= addr16; // Для операций с памятью
          default: address_o <= PC;
        endcase
      end
      MEM_S: begin
      case (opcode)
          4'h9:  address_o <= addr16;
          4'hA: address_o <= addr16; // Для операций с памятью
          default: address_o <= PC;
        endcase
      end
      INT_SAVE1_S, INT_JUMP_S: address_o <= IVT_ADDR;
      INT_SAVE2_S, INT_SAVE3_S: address_o <= IVT_ADDR + 16'b1;
      default: address_o <= PC;
    endcase
  end
endmodule

src/ram.sv
module ram (
  input clk_i,
  input rst_i,
  // A\D line
  input [15:0] address_i,
  input [7:0] data_i,
  input we_i,
  output logic [7:0] data_o
);

logic [7:0] mem [65536];

always_ff @( posedge clk_i ) begin
  if (we_i) mem [address_i] <= data_i;
end

always_ff @(posedge clk_i) begin
  data_o <= mem [address_i]; 
end
  
endmodule

src/top.sv
module top (
  input clk_i,
  input rst_i
);

wire [15:0] ram_address_line;
wire [7:0] ram_data_to_r_line;
wire [7:0] ram_data_from_r_line;
wire ram_we;

wire irq = 0;
wire [7:0] io_data_i;

ram u0(
  .clk_i         (clk_i),
  .rst_i         (rst_i),
  // A\D line
  .address_i     (ram_address_line),
  .data_i        (ram_data_to_r_line),
  .we_i          (ram_we),
  .data_o        (ram_data_from_r_line)
);

core u1(
  .clk_i         (clk_i),
  .rst_i         (rst_i),
  // A\D line
  .address_o     (ram_address_line),  
  .data_i        (ram_data_from_r_line),
  .we_i          (ram_we),              
  .data_o        (ram_data_to_r_line),
 // IO A\D line
  .irq_i         (irq),          
  .io_data_i     (io_data_i)     
);

  
endmodule

tb/tb_processor.sv
`timescale 1ns / 1ps

module tb_processor();

// Тактовый сигнал и сброс
reg clk = 0;
reg rst = 0;

// Подключение верхнего модуля
top dut (
    .clk_i(clk),
    .rst_i(rst)
);

always #5 clk = ~clk;

// ==============================================
// ТЕСТ 1: Базовые арифметические операции
// ==============================================
initial begin
  $dumpfile("dump.vcd"); $dumpvars;
   $monitor(" Registers: A=%h, B=%h, C=%h, D=%h", 
                 dut.u1.RF[0], dut.u1.RF[1], dut.u1.RF[2], dut.u1.RF[3]);

    rst = 1'b1;
    // Инициализация памяти для теста арифметики
    $readmemh("out.bin.hex", dut.u0.mem);
    #25
    rst = 1'b0;
    @(dut.u1.halt);
    #10
    $display(" Registers: A=%h, B=%h, C=%h, D=%h", 
                 dut.u1.RF[0], dut.u1.RF[1], dut.u1.RF[2], dut.u1.RF[3]);
    $display("  Flags: Z=%b, C=%b, V=%b, S=%b, IF=%b",
                 dut.u1.flags[0], dut.u1.flags[1], dut.u1.flags[2], 
                 dut.u1.flags[3], dut.u1.flags[4]);
    // Проверка результатов
    if (dut.u1.RF[0] != 8'h10 || dut.u1.RF[1] != 8'h02 || 
        dut.u1.flags[0] != 1'b0 || dut.u1.flags[1] != 1'b1) begin
        $display("TEST 1 FAILED!");
    end else begin
        $display("TEST 1 PASSED!");
    end

    $display("All tests completed");
    $finish;
end

endmodule

dump.vcd
$date
	Sun Mar 30 13:56:32 2025
$end
$version
	Icarus Verilog
$end
$timescale
	1ps
$end
$scope module tb_processor $end
$var reg 1 ! clk $end
$var reg 1 " rst $end
$scope module dut $end
$var wire 1 ! clk_i $end
$var wire 8 # io_data_i [7:0] $end
$var wire 1 $ irq $end
$var wire 1 " rst_i $end
$var wire 1 % ram_we $end
$var wire 8 & ram_data_to_r_line [7:0] $end
$var wire 8 ' ram_data_from_r_line [7:0] $end
$var wire 16 ( ram_address_line [15:0] $end
$scope module u0 $end
$var wire 1 ! clk_i $end
$var wire 1 " rst_i $end
$var wire 1 % we_i $end
$var wire 8 ) data_i [7:0] $end
$var wire 16 * address_i [15:0] $end
$var reg 8 + data_o [7:0] $end
$upscope $end
$scope module u1 $end
$var wire 1 ! clk_i $end
$var wire 8 , data_i [7:0] $end
$var wire 8 - imm8 [7:0] $end
$var wire 8 . io_data_i [7:0] $end
$var wire 1 $ irq_i $end
$var wire 1 " rst_i $end
$var wire 2 / reg2 [1:0] $end
$var wire 2 0 reg1 [1:0] $end
$var wire 4 1 opcode [3:0] $end
$var wire 16 2 addr16 [15:0] $end
$var parameter 4 3 DECODE_S $end
$var parameter 4 4 EXEC_S $end
$var parameter 4 5 FETCH2_S $end
$var parameter 4 6 FETCH3_S $end
$var parameter 4 7 FETCH_S $end
$var parameter 32 8 FLAG_C $end
$var parameter 32 9 FLAG_IF $end
$var parameter 32 : FLAG_S $end
$var parameter 32 ; FLAG_V $end
$var parameter 32 < FLAG_Z $end
$var parameter 4 = HALT_S $end
$var parameter 4 > IDLE_S $end
$var parameter 4 ? INT_JUMP2_S $end
$var parameter 4 @ INT_JUMP_S $end
$var parameter 4 A INT_SAVE1_S $end
$var parameter 4 B INT_SAVE2_S $end
$var parameter 4 C INT_SAVE3_S $end
$var parameter 16 D IVT_ADDR $end
$var parameter 4 E MEM_S $end
$var parameter 4 F V2_S $end
$var parameter 4 G V_S $end
$var parameter 4 H WB_S $end
$var reg 16 I PC [15:0] $end
$var reg 16 J SP [15:0] $end
$var reg 16 K address_o [15:0] $end
$var reg 8 L alu_result [7:0] $end
$var reg 9 M alu_result_ext [8:0] $end
$var reg 8 N data_o [7:0] $end
$var reg 8 O flags [7:0] $end
$var reg 1 P halt $end
$var reg 8 Q instruction [7:0] $end
$var reg 8 R instruction_2nd_byte [7:0] $end
$var reg 8 S instruction_3rd_byte [7:0] $end
$var reg 1 T int_pending $end
$var reg 8 U int_save_flags [7:0] $end
$var reg 16 V int_save_pc [15:0] $end
$var reg 8 W io_addr_o [7:0] $end
$var reg 8 X io_data_o [7:0] $end
$var reg 1 Y io_we_o $end
$var reg 1 Z irq_i_past $end
$var reg 4 [ state [3:0] $end
$var reg 1 % we_i $end
$upscope $end
$upscope $end
$upscope $end
$enddefinitions $end
$comment Show the parameter values. $end
$dumpall
b111 H
b1110 G
b1100 F
b110 E
b1111111111111110 D
b1010 C
b1001 B
b1000 A
b1011 @
b1111 ?
b0 >
b1101 =
b0 <
b10 ;
b11 :
b100 9
b1 8
b1 7
b100 6
b11 5
b101 4
b10 3
$end
#0
$dumpvars
bx [
xZ
xY
bx X
bx W
bx V
bx U
xT
bx S
bx R
bx Q
xP
bx O
bx N
bx M
bx L
bx K
bx J
bx I
bx 2
bx 1
bx 0
bx /
bz .
bx -
bx ,
bx +
bx *
bx )
bx (
bx '
bx &
x%
0$
bz #
0"
0!
$end
#5000
0Z
1!
#10000
b0 (
b0 *
b0 K
0T
0Y
0%
b0 O
b1111111111110000 J
b0 I
b0 [
0!
1"
#15000
0P
b10100000 '
b10100000 +
b10100000 ,
1!
#20000
0!
#25000
1!
#30000
0!
#35000
b1 [
1!
0"
#40000
0!
#45000
b1010 1
b0 0
b0 /
b10 [
b10100000 Q
1!
#50000
0!
#55000
b1 (
b1 *
b1 K
b1110 [
b1 I
1!
#60000
0!
#65000
b1 '
b1 +
b1 ,
b11 [
1!
#70000
0!
#75000
b10 (
b10 *
b10 K
b1100 [
b10 I
b1xxxxxxxx 2
b1 -
b1 R
1!
#80000
0!
#85000
b10 '
b10 +
b10 ,
b100 [
1!
#90000
0!
#95000
b100000010 (
b100000010 *
b100000010 K
b101 [
b100000010 2
b10 S
1!
#100000
0!
#105000
b1 '
b1 +
b1 ,
b110 [
1!
#110000
0!
#115000
b10 (
b10 *
b10 K
b111 [
1!
#120000
0!
#125000
b11 (
b11 *
b11 K
b10 '
b10 +
b10 ,
b0 [
b11 I
1!
#130000
0!
#135000
b10100001 '
b10100001 +
b10100001 ,
b1 [
1!
#140000
0!
#145000
b1 /
b10 [
b10100001 Q
1!
#150000
0!
#155000
b100 (
b100 *
b100 K
b1110 [
b100 I
1!
#160000
0!
#165000
b1 '
b1 +
b1 ,
b11 [
1!
#170000
0!
#175000
b101 (
b101 *
b101 K
b1100 [
b101 I
1!
#180000
0!
#185000
b11 '
b11 +
b11 ,
b100 [
1!
#190000
0!
#195000
b100000011 (
b100000011 *
b100000011 K
b101 [
b100000011 2
b11 S
1!
#200000
0!
#205000
b0 '
b0 +
b0 ,
b110 [
1!
#210000
0!
#215000
b101 (
b101 *
b101 K
b111 [
1!
#220000
0!
#225000
b110 (
b110 *
b110 K
b11 '
b11 +
b11 ,
b0 [
b110 I
1!
#230000
0!
#235000
b10010000 '
b10010000 +
b10010000 ,
b1 [
1!
#240000
0!
#245000
b1001 1
b0 /
b10 [
b10010000 Q
1!
#250000
0!
#255000
b111 (
b111 *
b111 K
b1110 [
b111 I
1!
#260000
0!
#265000
b1 '
b1 +
b1 ,
b11 [
1!
#270000
0!
#275000
b1000 (
b1000 *
b1000 K
b1100 [
b1000 I
1!
#280000
0!
#285000
b11 '
b11 +
b11 ,
b100 [
1!
#290000
0!
#295000
b100000011 (
b100000011 *
b100000011 K
b101 [
1!
#300000
0!
#305000
b0 '
b0 +
b0 ,
b110 [
1%
b1 &
b1 )
b1 N
1!
#310000
0!
#315000
b1000 (
b1000 *
b1000 K
b111 [
0%
1!
#320000
0!
#325000
b1001 (
b1001 *
b1001 K
b11 '
b11 +
b11 ,
b0 [
b1001 I
1!
#330000
0!
#335000
b100001 '
b100001 +
b100001 ,
b1 [
1!
#340000
0!
#345000
b10 1
b1 /
b10 [
b100001 Q
1!
#350000
0!
#355000
b101 [
1!
#360000
0!
#365000
b111 [
b1 M
1!
#370000
0!
#375000
b1010 (
b1010 *
b1010 K
b0 [
b1010 I
1!
#380000
0!
#385000
b10010000 '
b10010000 +
b10010000 ,
b1 [
1!
#390000
0!
#395000
b1001 1
b0 /
b10 [
b10010000 Q
1!
#400000
0!
#405000
b1011 (
b1011 *
b1011 K
b1110 [
b1011 I
1!
#410000
0!
#415000
b1 '
b1 +
b1 ,
b11 [
1!
#420000
0!
#425000
b1100 (
b1100 *
b1100 K
b1100 [
b1100 I
1!
#430000
0!
#435000
b10 '
b10 +
b10 ,
b100 [
1!
#440000
0!
#445000
b100000010 (
b100000010 *
b100000010 K
b101 [
b100000010 2
b10 S
1!
#450000
0!
#455000
b1 '
b1 +
b1 ,
b110 [
1%
1!
#460000
0!
#465000
b1100 (
b1100 *
b1100 K
b111 [
0%
1!
#470000
0!
#475000
b1101 (
b1101 *
b1101 K
b10 '
b10 +
b10 ,
b0 [
b1101 I
1!
#480000
0!
#485000
b10100010 '
b10100010 +
b10100010 ,
b1 [
1!
#490000
0!
#495000
b1010 1
b10 /
b10 [
b10100010 Q
1!
#500000
0!
#505000
b1110 (
b1110 *
b1110 K
b1110 [
b1110 I
1!
#510000
0!
#515000
b1 '
b1 +
b1 ,
b11 [
1!
#520000
0!
#525000
b1111 (
b1111 *
b1111 K
b1100 [
b1111 I
1!
#530000
0!
#535000
1Z
b100 [
1T
1!
1$
#540000
0!
#545000
b100000001 (
b100000001 *
b100000001 K
b101 [
b100000001 2
b1 S
1!
#550000
0!
#555000
b10 '
b10 +
b10 ,
b110 [
1!
#560000
0!
#565000
b1111 (
b1111 *
b1111 K
b111 [
1!
#570000
0!
#575000
b1111111111111110 (
b1111111111111110 *
b1111111111111110 K
b1 '
b1 +
b1 ,
0T
b1000 [
b10000 I
1!
#580000
0!
#585000
b1111111111111111 (
b1111111111111111 *
b1111111111111111 K
b0 '
b0 +
b0 ,
b1001 [
b0 U
b10000 V
1!
#590000
0!
#595000
b110000 '
b110000 +
b110000 ,
b1010 [
b0 I
1!
#600000
0!
#605000
b11000000000000 (
b11000000000000 *
b11000000000000 K
b0 [
b11000000000000 I
1!
#610000
0!
#615000
b10010011 '
b10010011 +
b10010011 ,
b1 [
1!
#620000
0!
#625000
b1001 1
b11 /
b10 [
b10010011 Q
1!
#630000
0!
#635000
b11000000000001 (
b11000000000001 *
b11000000000001 K
0Z
b1110 [
b11000000000001 I
1!
0$
#640000
0!
#645000
b1 '
b1 +
b1 ,
b11 [
1!
#650000
0!
#655000
b11000000000010 (
b11000000000010 *
b11000000000010 K
b1100 [
b11000000000010 I
1!
#660000
0!
#665000
b101 '
b101 +
b101 ,
b100 [
1!
#670000
0!
#675000
b100000101 (
b100000101 *
b100000101 K
b101 [
b100000101 2
b101 S
1!
#680000
0!
#685000
b1 '
b1 +
b1 ,
b110 [
1%
b0 &
b0 )
b0 N
1!
#690000
0!
#695000
b11000000000010 (
b11000000000010 *
b11000000000010 K
b111 [
0%
1!
#700000
0!
#705000
b11000000000011 (
b11000000000011 *
b11000000000011 K
b101 '
b101 +
b101 ,
b0 [
b11000000000011 I
1!
#710000
0!
#715000
b1110011 '
b1110011 +
b1110011 ,
b1 [
1!
#720000
0!
#725000
b111 1
b10 [
b1110011 Q
1!
#730000
0!
#735000
b11000000000100 (
b11000000000100 *
b11000000000100 K
b1110 [
b11000000000100 I
1!
#740000
0!
#745000
b1011 '
b1011 +
b1011 ,
b11 [
1!
#750000
0!
#755000
b101 [
b101100000101 2
b1011 -
b1011 R
1!
#760000
0!
#765000
b111 [
b1011 L
1!
#770000
0!
#775000
b11000000000101 (
b11000000000101 *
b11000000000101 K
b0 [
b11000000000101 I
1!
#780000
0!
#785000
b10010011 '
b10010011 +
b10010011 ,
b1 [
1!
#790000
0!
#795000
b1001 1
b10 [
b10010011 Q
1!
#800000
0!
#805000
b11000000000110 (
b11000000000110 *
b11000000000110 K
b1110 [
b11000000000110 I
1!
#810000
0!
#815000
b1 '
b1 +
b1 ,
b11 [
1!
#820000
0!
#825000
b11000000000111 (
b11000000000111 *
b11000000000111 K
b1100 [
b11000000000111 I
b100000101 2
b1 -
b1 R
1!
#830000
0!
#835000
b0 '
b0 +
b0 ,
b100 [
1!
#840000
0!
#845000
b100000000 (
b100000000 *
b100000000 K
b101 [
b100000000 2
b0 S
1!
#850000
0!
#855000
b1010 '
b1010 +
b1010 ,
b110 [
1%
b1011 &
b1011 )
b1011 N
1!
#860000
0!
#865000
b11000000000111 (
b11000000000111 *
b11000000000111 K
b111 [
0%
1!
#870000
0!
#875000
b11000000001000 (
b11000000001000 *
b11000000001000 K
b0 '
b0 +
b0 ,
b0 [
b11000000001000 I
1!
#880000
0!
#885000
b10100011 '
b10100011 +
b10100011 ,
b1 [
1!
#890000
0!
#895000
b1010 1
b10 [
b10100011 Q
1!
#900000
0!
#905000
b11000000001001 (
b11000000001001 *
b11000000001001 K
b1110 [
b11000000001001 I
1!
#910000
0!
#915000
b1 '
b1 +
b1 ,
b11 [
1!
#920000
0!
#925000
b11000000001010 (
b11000000001010 *
b11000000001010 K
b1100 [
b11000000001010 I
1!
#930000
0!
#935000
b101 '
b101 +
b101 ,
b100 [
1!
#940000
0!
#945000
b100000101 (
b100000101 *
b100000101 K
b101 [
b100000101 2
b101 S
1!
#950000
0!
#955000
b0 '
b0 +
b0 ,
b110 [
1!
#960000
0!
#965000
b11000000001010 (
b11000000001010 *
b11000000001010 K
b111 [
1!
#970000
0!
#975000
b11000000001011 (
b11000000001011 *
b11000000001011 K
b101 '
b101 +
b101 ,
b0 [
b11000000001011 I
1!
#980000
0!
#985000
b11100001 '
b11100001 +
b11100001 ,
b1 [
1!
#990000
0!
#995000
b1110 1
b1 /
b10 [
b11100001 Q
1!
#1000000
0!
#1005000
b101 [
1!
#1010000
0!
#1015000
b10000 (
b10000 *
b10000 K
b111 [
b10000 I
1!
#1020000
0!
#1025000
b10001 (
b10001 *
b10001 K
b1110011 '
b1110011 +
b1110011 ,
b0 [
b10001 I
1!
#1030000
0!
#1035000
b1 '
b1 +
b1 ,
b1 [
1!
#1040000
0!
#1045000
b0 1
b10 [
b1 Q
1!
#1050000
0!
#1055000
b101 [
1!
#1060000
0!
#1065000
b111 [
1!
#1070000
0!
#1075000
b10010 (
b10010 *
b10010 K
b0 [
b10010 I
1!
#1080000
0!
#1085000
b101011 '
b101011 +
b101011 ,
b1 [
1!
#1090000
0!
#1095000
b10 1
b10 0
b11 /
b10 [
b101011 Q
1!
#1100000
0!
#1105000
b101 [
1!
#1110000
0!
#1115000
b111 [
b10 M
1!
#1120000
0!
#1125000
b10011 (
b10011 *
b10011 K
b0 [
b10011 I
1!
#1130000
0!
#1135000
b10100011 '
b10100011 +
b10100011 ,
b1 [
1!
#1140000
0!
#1145000
b1010 1
b0 0
b10 [
b10100011 Q
1!
#1150000
0!
#1155000
b10100 (
b10100 *
b10100 K
b1110 [
b10100 I
1!
#1160000
0!
#1165000
b1 '
b1 +
b1 ,
b11 [
1!
#1170000
0!
#1175000
b10101 (
b10101 *
b10101 K
b1100 [
b10101 I
1!
#1180000
0!
#1185000
b0 '
b0 +
b0 ,
b100 [
1!
#1190000
0!
#1195000
b100000000 (
b100000000 *
b100000000 K
b101 [
b100000000 2
b0 S
1!
#1200000
0!
#1205000
b1011 '
b1011 +
b1011 ,
b110 [
1!
#1210000
0!
#1215000
b10101 (
b10101 *
b10101 K
b111 [
1!
#1220000
0!
#1225000
b10110 (
b10110 *
b10110 K
b0 '
b0 +
b0 ,
b0 [
b10110 I
1!
#1230000
0!
#1235000
b111110 '
b111110 +
b111110 ,
b1 [
1!
#1240000
0!
#1245000
b11 1
b11 0
b10 /
b10 [
b111110 Q
1!
#1250000
0!
#1255000
b101 [
1!
#1260000
0!
#1265000
b111 [
b1001 M
1!
#1270000
0!
#1275000
b10111 (
b10111 *
b10111 K
b0 [
b10111 I
1!
#1280000
0!
#1285000
b10010010 '
b10010010 +
b10010010 ,
b1 [
1!
#1290000
0!
#1295000
b1001 1
b0 0
b10 [
b10010010 Q
1!
#1300000
0!
#1305000
b11000 (
b11000 *
b11000 K
b1110 [
b11000 I
1!
#1310000
0!
#1315000
b1 '
b1 +
b1 ,
b11 [
1!
#1320000
0!
#1325000
b11001 (
b11001 *
b11001 K
b1100 [
b11001 I
1!
#1330000
0!
#1335000
b100 [
1!
#1340000
0!
#1345000
b100000001 (
b100000001 *
b100000001 K
b101 [
b100000001 2
b1 S
1!
#1350000
0!
#1355000
b10 '
b10 +
b10 ,
b110 [
1%
b10 &
b10 )
b10 N
1!
#1360000
0!
#1365000
b11001 (
b11001 *
b11001 K
b111 [
0%
1!
#1370000
0!
#1375000
b11010 (
b11010 *
b11010 K
b1 '
b1 +
b1 ,
b0 [
b11010 I
1!
#1380000
0!
#1385000
b11010001 '
b11010001 +
b11010001 ,
b1 [
1!
#1390000
0!
#1395000
b1101 1
b1 /
b10 [
b11010001 Q
1!
#1400000
0!
#1405000
b11011 (
b11011 *
b11011 K
b1110 [
b11011 I
1!
#1410000
0!
#1415000
b0 '
b0 +
b0 ,
b11 [
1!
#1420000
0!
#1425000
b11100 (
b11100 *
b11100 K
b1100 [
b11100 I
b1 2
b0 -
b0 R
1!
#1430000
0!
#1435000
b100000 '
b100000 +
b100000 ,
b100 [
1!
#1440000
0!
#1445000
b101 [
b100000 2
b100000 S
1!
#1450000
0!
#1455000
b111 [
1!
#1460000
0!
#1465000
b0 [
1!
#1470000
0!
#1475000
b1 [
1!
#1480000
0!
#1485000
b10 1
b0 /
b10 [
b100000 Q
1!
#1490000
0!
#1495000
b101 [
1!
#1500000
0!
#1505000
b111 [
b10 M
1!
#1510000
0!
#1515000
b11101 (
b11101 *
b11101 K
b0 [
b11101 I
1!
#1520000
0!
#1525000
b11010000 '
b11010000 +
b11010000 ,
b1 [
1!
#1530000
0!
#1535000
b1101 1
b10 [
b11010000 Q
1!
#1540000
0!
#1545000
b11110 (
b11110 *
b11110 K
b1110 [
b11110 I
1!
#1550000
0!
#1555000
b0 '
b0 +
b0 ,
b11 [
1!
#1560000
0!
#1565000
b11111 (
b11111 *
b11111 K
b1100 [
b11111 I
1!
#1570000
0!
#1575000
b100 [
1!
#1580000
0!
#1585000
b101 [
b0 2
b0 S
1!
#1590000
0!
#1595000
b0 (
b0 *
b0 K
b111 [
b0 I
1!
#1600000
0!
#1605000
b10100000 '
b10100000 +
b10100000 ,
b0 [
1!
#1610000
0!
#1615000
b1 [
1!
#1620000
0!
#1625000
b1010 1
b10 [
b10100000 Q
1!
#1630000
0!
#1635000
b1 (
b1 *
b1 K
b1110 [
b1 I
1!
#1640000
0!
#1645000
b1 '
b1 +
b1 ,
b11 [
1!
#1650000
0!
#1655000
b10 (
b10 *
b10 K
b1100 [
b10 I
b100000000 2
b1 -
b1 R
1!
#1660000
0!
#1665000
b10 '
b10 +
b10 ,
b100 [
1!
#1670000
0!
