src/rtc.sv
module rtc (
  input clk_i,
  input rst_i,
  // IO Interface
  output reg irq_o,
  output [31:0] current_millis
);

localparam CLK_FREQ = 50_000_000;    // Пример: 50 МГц
localparam MS_DIVIDER = CLK_FREQ / 1000;

reg [31:0] milliseconds;
reg [15:0] counter;

always @(posedge clk_i or posedge rst_i) begin
  if (rst_i) begin
    counter <= 0;
    milliseconds <= 0;
    irq_o <= 0;
  end else begin
    // Обновление счетчика
    if (counter >= MS_DIVIDER - 1) begin
      counter <= 0;
      milliseconds <= milliseconds + 1;
      irq_o <= 1;
    end else begin
      counter <= counter + 1;
      irq_o <= 0;
    end
  end
end

assign current_millis = milliseconds;

endmodule

src/core.sv
module core(
  input clk_i,
  input rst_i,
  // Работа с внешними устройствами
  input irq_i,          // Сигнал прерывания
  input [7:0] io_data_i,// Данные от устройств ввода
  output reg [7:0] io_data_o,// Данные для устройств вывода
  output reg [7:0] io_addr_o,// Адрес устройства ввода/вывода
  output reg io_we_o,   // Сигнал записи в устройство вывода
  // Интерфейс памяти
  output reg [15:0] address_o,  
  input [7:0] data_i,
  output reg we_i,              
  output reg [7:0] data_o
);

  // Состояния конечного автомата
  localparam IDLE_S     = 4'd0;
  localparam FETCH_S    = 4'd1;
  localparam DECODE_S   = 4'd2;
  localparam FETCH2_S   = 4'd3;
  localparam FETCH3_S   = 4'd4;
  localparam EXEC_S     = 4'd5;
  localparam MEM_S      = 4'd6;
  localparam WB_S       = 4'd7;
  localparam HALT_S     = 4'd13; // Состояние останова
  localparam V_S        = 4'd14;
  localparam V2_S = 4'd12;
  localparam INT_SAVE1_S = 4'd8; // Сохранение PC младший байт
  localparam INT_SAVE2_S = 4'd9; // Сохранение PC старший байт
  localparam INT_SAVE3_S = 4'd10; // Сохранение флагов
  localparam INT_JUMP_S = 4'd11;  // Переход к обработчику
  localparam INT_JUMP2_S = 4'd15;

  // Определение битов флагов
  localparam FLAG_Z     = 0; // Zero
  localparam FLAG_C     = 1; // Carry
  localparam FLAG_V     = 2; // Overflow
  localparam FLAG_S     = 3; // Sign
  localparam FLAG_IF    = 4; // Interrupt Flag

  // Адрес вектора прерываний
  localparam IVT_ADDR   = 16'hFFFE;

  // Регистры процессора
  reg [3:0] state;
  reg [7:0] RF [0:3];  // Регистровый файл (A=0, B=1, C=2, D=3)
  reg [15:0] PC;       // Счетчик команд
  reg [15:0] SP;       // Указатель стека
  reg [7:0] flags;     // Регистр флагов
  
  // Регистры для хранения инструкций
  reg [7:0] instruction;
  reg [7:0] instruction_2nd_byte;
  reg [7:0] instruction_3rd_byte;
  
  // Временные регистры
  reg [7:0] alu_result;
  reg [8:0] alu_result_ext; // 9 бит для учета переноса

  reg [15:0] int_save_pc;   
  reg [15:0] int_load_pc; 
  reg [7:0] int_save_flags;   
  reg int_pending;          // Флаг ожидания прерывания
  reg irq_i_past;
  // Комбинационные сигналы
  wire [3:0] opcode = instruction[7:4];
  wire [1:0] reg1 = instruction[3:2];
  wire [1:0] reg2 = instruction[1:0];
  wire [7:0] imm8 = instruction_2nd_byte;
  wire [15:0] addr16 = {instruction_2nd_byte, instruction_3rd_byte};


  always_ff @(posedge clk_i) begin
     irq_i_past <= irq_i;
  end

  // Логика следующего состояния
  always @(posedge clk_i or posedge rst_i) begin
    if (irq_i_past == 1'b0 && irq_i == 1'b1) int_pending <= 1'b1;
    if (rst_i) begin
      state <= IDLE_S;
      PC <= 16'h0000;
      SP <= 16'hFFF0;
      flags <= 8'b00000000;
      we_i <= 1'b0;
      io_we_o <= 1'b0;
      int_pending <= 1'b0;
      irq_i_past <= 1'b0;
      RF[0] <= '0;
      RF[1] <= '0;
      RF[2] <= '0;
      RF[3] <= '0;
    end else begin
      case (state)
        IDLE_S: begin
          if (!halt) state <= FETCH_S;
        end
        
        FETCH_S: begin
          instruction <= data_i;
          state <= DECODE_S;
        end
        
        DECODE_S: begin
          case (opcode)
            // 2-байтовые команды
            4'h7, 4'h8, 4'hB, 4'hC: begin
              PC <= PC + 1;
              state <= V_S;
              
            end
            // 3-байтовые команды
            4'h9, 4'hA, 4'hD: begin
              PC <= PC + 1;
              state <= V_S;
            end
            // 1-байтовые команды
            default: state <= EXEC_S;
          endcase
        end
        
        V_S: state <= FETCH2_S;

        FETCH2_S: begin
          instruction_2nd_byte <= data_i;
          case (opcode)
            // 3-байтовые команды
            4'h9, 4'hA, 4'hD: begin
              PC <= PC + 1;
              state <= V2_S;
            end
            // 2-байтовые команды
            default: state <= EXEC_S;
          endcase
        end
        
        V2_S: state <= FETCH3_S;

        FETCH3_S: begin
          instruction_3rd_byte <= data_i;
          state <= EXEC_S;
        end
        
        EXEC_S: begin
          // Выполнение операции
          case (opcode)
            // MOV R1, R2
            4'h1: alu_result <= RF[reg2];
            
            // ADD R1, R2
            4'h2: alu_result_ext <= RF[reg1] + RF[reg2];
            
            // SUB R1, R2
            4'h3: alu_result_ext <= RF[reg1] - RF[reg2];
            
            // AND R1, R2
            4'h4: alu_result <= RF[reg1] & RF[reg2];
            
            // OR R1, R2
            4'h5: alu_result <= RF[reg1] | RF[reg2];
            
            // XOR R1, R2
            4'h6: alu_result <= RF[reg1] ^ RF[reg2];
            
            // MOV R, IMM8
            4'h7: alu_result <= imm8;
            
            // ADD R, IMM8
            4'h8: alu_result_ext <= RF[reg1] + imm8;
            
            // MOV [ADDR16], R
            4'h9: begin
              address_o <= addr16;
              data_o <= RF[reg2];
              we_i <= 1'b1;
            end
            
            // MOV R, [ADDR16]
            4'hA: begin
              address_o <= addr16;
            end
            
            // IN R, PORT8
            4'hB: begin
              io_addr_o <= imm8;
              io_we_o <= 1'b0;
            end
            
            // OUT PORT8, R
            4'hC: begin
              io_addr_o <= imm8;
              io_data_o <= RF[reg1];
              io_we_o <= 1'b1;
            end
            
            // JMP/JZ/JC ADDR16
            4'hD: begin
              case (instruction[3:0])
                4'd0: PC <= addr16; // JMP
                4'd1: if (flags[FLAG_Z]) PC <= addr16; // JZ
                4'd2: if (flags[FLAG_C]) PC <= addr16; // JC
              endcase
            end
            
            // EI/DI
            4'hE: begin
              case (instruction[3:0])
                4'h1: begin
                  flags <= int_save_flags;
                  PC <= int_save_pc;
                  state <= IDLE_S;
                end
                4'h2: flags[FLAG_IF] <= 1'b1; // EI
                4'h3: flags[FLAG_IF] <= 1'b0; // DI
                4'hF: begin /* HALT - обрабатывается отдельно */ end
              endcase
            end
          endcase
          
          // Переход в следующее состояние
          if (opcode == 4'h9 || opcode == 4'hA || opcode == 4'hB || opcode == 4'hC) begin
            state <= MEM_S;
          end else begin
            state <= WB_S;
          end
        end
        
        MEM_S: begin
          we_i <= 1'b0;
          io_we_o <= 1'b0;
          state <= WB_S;
        end
        
        WB_S: begin
          case (opcode)
            // MOV R1, R2
            4'h1: RF[reg1] <= alu_result;
            
            // ADD R1, R2
            4'h2: begin
              RF[reg1] <= alu_result_ext[7:0];
              flags[FLAG_Z] <= (alu_result_ext[7:0] == 8'b0);
              flags[FLAG_C] <= alu_result_ext[8];
              flags[FLAG_V] <= (RF[reg1][7] == RF[reg2][7]) && 
                              (alu_result_ext[7] != RF[reg1][7]);
              flags[FLAG_S] <= alu_result_ext[7];
            end
            
            // SUB R1, R2
            4'h3: begin
              RF[reg1] <= alu_result_ext[7:0];
              flags[FLAG_Z] <= (alu_result_ext[7:0] == 8'b0);
              flags[FLAG_C] <= alu_result_ext[8];
              flags[FLAG_V] <= (RF[reg1][7] != RF[reg2][7]) && 
                              (alu_result_ext[7] != RF[reg1][7]);
              flags[FLAG_S] <= alu_result_ext[7];
            end
            
            // AND/OR/XOR R1, R2
            4'h4, 4'h5, 4'h6: begin
              RF[reg1] <= alu_result;
              flags[FLAG_Z] <= (alu_result == 8'b0);
              flags[FLAG_S] <= alu_result[7];
              flags[FLAG_C] <= 1'b0;
              flags[FLAG_V] <= 1'b0;
            end
            
            // MOV R, IMM8
            4'h7: RF[reg2] <= alu_result;
            
            // ADD R, IMM8
            4'h8: begin
              RF[reg1] <= alu_result_ext[7:0];
              flags[FLAG_Z] <= (alu_result_ext[7:0] == 8'b0);
              flags[FLAG_C] <= alu_result_ext[8];
              flags[FLAG_V] <= (RF[reg1][7] == imm8[7]) && 
                              (alu_result_ext[7] != RF[reg1][7]);
              flags[FLAG_S] <= alu_result_ext[7];
            end
            
            // MOV R, [ADDR16]
            4'hA: RF[reg2] <= data_i;
            
            // IN R, PORT8
            4'hB: RF[reg1] <= io_data_i;
          endcase
          
          // Обновление PC для всех команд кроме JMP/JZ/JC
          if (opcode != 4'hD) begin
            PC <= PC + 1;
          end
          
          // Проверяем, есть ли ожидающее прерывание
          if (int_pending) begin
            state <= INT_SAVE1_S;
            int_pending <= 1'b0;
          end else begin
            state <= IDLE_S;
          end
        end
        
        // Сохранение младшего байта PC
        INT_SAVE1_S: begin
          int_save_pc <= PC;
          int_save_flags <= flags;
          state <= INT_SAVE2_S;
        end
        
        // Сохранение старшего байта PC
        INT_SAVE2_S: begin
          PC <= data_i;
          state <= INT_SAVE3_S;
        end
        
        // Сохранение флагов
        INT_SAVE3_S: begin
          PC[15:8] <= data_i; // Читаем адрес обработчика
          state <= IDLE_S;
        end
        
        HALT_S: begin
          // Останов процессора
          if (irq_i && flags[FLAG_IF]) begin
            int_pending <= 1'b1;
            state <= INT_SAVE1_S;
          end
        end
      endcase
    end
  end

  // Логика прерываний
  always @(posedge clk_i) begin
    if (rst_i) begin
      int_pending <= 1'b0;
    end else if (irq_i && flags[FLAG_IF] && !halt && !int_pending) begin
      // Запоминаем запрос прерывания, если он разрешен
      int_pending <= 1'b1;
    end else if (state == INT_JUMP_S) begin
      // Сбрасываем флаг после перехода к обработчику
      int_pending <= 1'b0;
    end
  end


  // Останов процессора
  reg halt;
  always @(posedge clk_i) begin
    if (rst_i) begin
      halt <= 1'b0;
    end else if (state == EXEC_S && opcode == 4'hE && instruction[3:0] == 4'hF) begin
      halt <= 1'b1;
      state <= HALT_S;
    end
  end

  // Управление адресом памяти
  always @(*) begin
    case (state)
      V_S, V2_S, FETCH_S, FETCH2_S, FETCH3_S: address_o <= PC;
      EXEC_S: begin
        case (opcode)
          4'h9, 4'hA: address_o <= addr16; // Для операций с памятью
          default: address_o <= PC;
        endcase
      end
      MEM_S: begin
      case (opcode)
          4'h9:  address_o <= addr16;
          4'hA: address_o <= addr16; // Для операций с памятью
          default: address_o <= PC;
        endcase
      end
      INT_SAVE1_S, INT_JUMP_S: address_o <= IVT_ADDR;
      INT_SAVE2_S, INT_SAVE3_S: address_o <= IVT_ADDR + 16'b1;
      default: address_o <= PC;
    endcase
  end
endmodule

src/ram.sv
module ram (
  input clk_i,
  input rst_i,
  // A\D line
  input [15:0] address_i,
  input [7:0] data_i,
  input we_i,
  output logic [7:0] data_o
);

logic [7:0] mem [65536];

always_ff @( posedge clk_i ) begin
  if (we_i) mem [address_i] <= data_i;
end

always_ff @(posedge clk_i) begin
  data_o <= mem [address_i]; 
end
  
endmodule

src/top.sv
module top (
  input clk_i,
  input rst_i
);

// RAM signals
wire [15:0] ram_address_line;
wire [7:0] ram_data_to_r_line;
wire [7:0] ram_data_from_r_line;
wire ram_we;

// Core IO signals
logic [7:0] io_data_i;
wire [7:0] io_data_o;
wire [7:0] io_addr_o;
wire io_we_o;

// RTC signals
wire rtc_irq;
wire [31:0] rtc_snap_millis;

logic [7:0] device_id;

// Чтение данных
always_comb begin
  case(io_addr_o)
    0: io_data_i = device_id;
    1: io_data_i = rtc_snap_millis[7:0];
    2: io_data_i = rtc_snap_millis[15:8];
    3: io_data_i = rtc_snap_millis[23:16];
    4: io_data_i = rtc_snap_millis[31:24];
    default: io_data_i = 8'b0;
  endcase
end

always_comb begin
  if (rtc_irq) device_id = 8'h1; //RTC
  else device_id = 8'h0;
end


ram u0(
  .clk_i         (clk_i),
  .rst_i         (rst_i),
  // A\D line
  .address_i     (ram_address_line),
  .data_i        (ram_data_to_r_line),
  .we_i          (ram_we),
  .data_o        (ram_data_from_r_line)
);

core u1(
  .clk_i         (clk_i),
  .rst_i         (rst_i),
  // Memory interface
  .address_o     (ram_address_line),
  .data_i        (ram_data_from_r_line),
  .we_i          (ram_we),
  .data_o        (ram_data_to_r_line),
  // IO interface
  .irq_i         (rtc_irq),
  .io_data_i     (io_data_i),
  .io_data_o     (io_data_o),
  .io_addr_o     (io_addr_o),
  .io_we_o       (io_we_o)
);


rtc u2(
  .clk_i              (clk_i),
  .rst_i              (rst_i),
  .current_millis     (rtc_snap_millis),
  .irq_o              (rtc_irq)
);
  
endmodule

tb/tb_processor.sv
`timescale 1ns / 1ps

module tb_processor();

// Тактовый сигнал и сброс
reg clk = 0;
reg rst = 0;

// Подключение верхнего модуля
top dut (
    .clk_i(clk),
    .rst_i(rst)
);

always #5 clk = ~clk;

// ==============================================
// ТЕСТ 1: Базовые арифметические операции
// ==============================================
initial begin
   $dumpfile("dump.vcd"); $dumpvars;
   /*
   //$monitor(" Registers: A=%h, B=%h, C=%h, D=%h, 0=%h, 1=%h, 2=%h, 3=%h", 
                 dut.u1.RF[0], dut.u1.RF[1], dut.u1.RF[2], dut.u1.RF[3], dut.u0.mem[16'h0100], dut.u0.mem[16'h0101], dut.u0.mem[16'h0102], dut.u0.mem[16'h0103]);
    rst = 1'b1;
    // Инициализация памяти для теста арифметики
    $readmemh("out.bin.hex", dut.u0.mem);
    #25
    rst = 1'b0;
    @(dut.u1.halt);
    #10
    $display(" Registers: A=%h, B=%h, C=%h, D=%h", 
                 dut.u1.RF[0], dut.u1.RF[1], dut.u1.RF[2], dut.u1.RF[3]);
    $display("  Flags: Z=%b, C=%b, V=%b, S=%b, IF=%b",
                 dut.u1.flags[0], dut.u1.flags[1], dut.u1.flags[2], 
                 dut.u1.flags[3], dut.u1.flags[4]);
    // Проверка результатов
    if (dut.u1.RF[0] != 8'h10 || dut.u1.RF[1] != 8'h02 || 
        dut.u1.flags[0] != 1'b0 || dut.u1.flags[1] != 1'b1) begin
        $display("TEST 1 FAILED!");
    end else begin
        $display("TEST 1 PASSED!");
    end
    #10
    rst = 1'b1;
    // Инициализация памяти для теста арифметики
    $readmemh("out2.bin.hex", dut.u0.mem);
    #25
    rst = 1'b0;
    @(dut.u1.halt);
    #10
    if (dut.u1.RF[1] != 8'h05 || dut.u0.mem[16'h0100] != 8'h05) begin
        $display("TEST 2 FAILED!");
    end else begin
        $display("TEST 2 PASSED!");
    end

    */
    #10
    rst = 1'b1;
    // Инициализация памяти для теста арифметики
    $readmemh("out4.bin.hex", dut.u0.mem);
    #25
    rst = 1'b0;
    @(dut.u2.irq_o);
    #100
    $display(" Registers: A=%h, B=%h, C=%h, D=%h", 
                 dut.u1.RF[0], dut.u1.RF[1], dut.u1.RF[2], dut.u1.RF[3]);
    $display("  Flags: Z=%b, C=%b, V=%b, S=%b, IF=%b",
                 dut.u1.flags[0], dut.u1.flags[1], dut.u1.flags[2], 
                 dut.u1.flags[3], dut.u1.flags[4]);
    $display(" Registers: A=%h, B=%h, C=%h, D=%h, 0=%h, 1=%h, 2=%h, 3=%h", 
                 dut.u1.RF[0], dut.u1.RF[1], dut.u1.RF[2], dut.u1.RF[3], dut.u0.mem[16'h0100], dut.u0.mem[16'h0101], dut.u0.mem[16'h0102], dut.u0.mem[16'h0105]);
    $display("All tests completed");
    $finish;
end

endmodule

dump.vcd
$date
	Sun Mar 30 15:18:34 2025
$end
$version
	Icarus Verilog
$end
$timescale
	1ps
$end
$scope module tb_processor $end
$var reg 1 ! clk $end
$var reg 1 " rst $end
$scope module dut $end
$var wire 1 ! clk_i $end
$var wire 1 " rst_i $end
$var wire 32 # rtc_snap_millis [31:0] $end
$var wire 1 $ rtc_irq $end
$var wire 1 % ram_we $end
$var wire 8 & ram_data_to_r_line [7:0] $end
$var wire 8 ' ram_data_from_r_line [7:0] $end
$var wire 16 ( ram_address_line [15:0] $end
$var wire 1 ) io_we_o $end
$var wire 8 * io_data_o [7:0] $end
$var wire 8 + io_addr_o [7:0] $end
$var reg 8 , device_id [7:0] $end
$var reg 8 - io_data_i [7:0] $end
$scope module u0 $end
$var wire 1 ! clk_i $end
$var wire 1 " rst_i $end
$var wire 1 % we_i $end
$var wire 8 . data_i [7:0] $end
$var wire 16 / address_i [15:0] $end
$var reg 8 0 data_o [7:0] $end
$upscope $end
$scope module u1 $end
$var wire 1 ! clk_i $end
$var wire 8 1 data_i [7:0] $end
$var wire 8 2 imm8 [7:0] $end
$var wire 8 3 io_data_i [7:0] $end
$var wire 1 " rst_i $end
$var wire 2 4 reg2 [1:0] $end
$var wire 2 5 reg1 [1:0] $end
$var wire 4 6 opcode [3:0] $end
$var wire 1 $ irq_i $end
$var wire 16 7 addr16 [15:0] $end
$var parameter 4 8 DECODE_S $end
$var parameter 4 9 EXEC_S $end
$var parameter 4 : FETCH2_S $end
$var parameter 4 ; FETCH3_S $end
$var parameter 4 < FETCH_S $end
$var parameter 32 = FLAG_C $end
$var parameter 32 > FLAG_IF $end
$var parameter 32 ? FLAG_S $end
$var parameter 32 @ FLAG_V $end
$var parameter 32 A FLAG_Z $end
$var parameter 4 B HALT_S $end
$var parameter 4 C IDLE_S $end
$var parameter 4 D INT_JUMP2_S $end
$var parameter 4 E INT_JUMP_S $end
$var parameter 4 F INT_SAVE1_S $end
$var parameter 4 G INT_SAVE2_S $end
$var parameter 4 H INT_SAVE3_S $end
$var parameter 16 I IVT_ADDR $end
$var parameter 4 J MEM_S $end
$var parameter 4 K V2_S $end
$var parameter 4 L V_S $end
$var parameter 4 M WB_S $end
$var reg 16 N PC [15:0] $end
$var reg 16 O SP [15:0] $end
$var reg 16 P address_o [15:0] $end
$var reg 8 Q alu_result [7:0] $end
$var reg 9 R alu_result_ext [8:0] $end
$var reg 8 S data_o [7:0] $end
$var reg 8 T flags [7:0] $end
$var reg 1 U halt $end
$var reg 8 V instruction [7:0] $end
$var reg 8 W instruction_2nd_byte [7:0] $end
$var reg 8 X instruction_3rd_byte [7:0] $end
$var reg 1 Y int_pending $end
$var reg 8 Z int_save_flags [7:0] $end
$var reg 16 [ int_save_pc [15:0] $end
$var reg 8 \ io_addr_o [7:0] $end
$var reg 8 ] io_data_o [7:0] $end
$var reg 1 ) io_we_o $end
$var reg 1 ^ irq_i_past $end
$var reg 4 _ state [3:0] $end
$var reg 1 % we_i $end
$upscope $end
$scope module u2 $end
$var wire 1 ! clk_i $end
$var wire 32 ` current_millis [31:0] $end
$var wire 1 " rst_i $end
$var parameter 32 a CLK_FREQ $end
$var parameter 32 b MS_DIVIDER $end
$var reg 16 c counter [15:0] $end
$var reg 1 $ irq_o $end
$var reg 32 d milliseconds [31:0] $end
$upscope $end
$upscope $end
$upscope $end
$enddefinitions $end
$comment Show the parameter values. $end
$dumpall
b1100001101010000 b
b10111110101111000010000000 a
b111 M
b1110 L
b1100 K
b110 J
b1111111111111110 I
b1010 H
b1001 G
b1000 F
b1011 E
b1111 D
b0 C
b1101 B
b0 A
b10 @
b11 ?
b100 >
b1 =
b1 <
b100 ;
b11 :
b101 9
b10 8
$end
#0
$dumpvars
bx d
bx c
bx `
bx _
x^
bx ]
bx \
bx [
bx Z
xY
bx X
bx W
bx V
xU
bx T
bx S
bx R
bx Q
bx P
bx O
bx N
bx 7
bx 6
bx 5
bx 4
b0 3
bx 2
bx 1
bx 0
bx /
bx .
b0 -
b0 ,
bx +
bx *
x)
bx (
bx '
bx &
x%
x$
bx #
0"
0!
$end
#5000
0$
1!
#10000
b0 (
b0 /
b0 P
b0 #
b0 `
b0 d
b0 c
0^
0Y
0)
0%
b0 T
b1111111111110000 O
b0 N
b0 _
0!
1"
#15000
0U
b10100000 '
b10100000 0
b10100000 1
1!
#20000
0!
#25000
1!
#30000
0!
#35000
b1 _
b1 c
1!
0"
#40000
0!
#45000
b1010 6
b0 5
b0 4
b10 c
b10 _
b10100000 V
1!
#50000
0!
#55000
b1 (
b1 /
b1 P
b1110 _
b1 N
b11 c
1!
#60000
0!
#65000
b1 '
b1 0
b1 1
b100 c
b11 _
1!
#70000
0!
#75000
b10 (
b10 /
b10 P
b1100 _
b10 N
b1xxxxxxxx 7
b1 2
b1 W
b101 c
1!
#80000
0!
#85000
b10 '
b10 0
b10 1
b110 c
b100 _
1!
#90000
0!
#95000
b100000010 (
b100000010 /
b100000010 P
b101 _
b100000010 7
b10 X
b111 c
1!
#100000
0!
#105000
b1 '
b1 0
b1 1
b1000 c
b110 _
1!
#110000
0!
#115000
b10 (
b10 /
b10 P
b111 _
b1001 c
1!
#120000
0!
#125000
b11 (
b11 /
b11 P
b10 '
b10 0
b10 1
b1010 c
b0 _
b11 N
1!
#130000
0!
#135000
b10100001 '
b10100001 0
b10100001 1
b1 _
b1011 c
1!
#140000
0!
#145000
b1 4
b1100 c
b10 _
b10100001 V
1!
#150000
0!
#155000
b100 (
b100 /
b100 P
b1110 _
b100 N
b1101 c
1!
#160000
0!
#165000
b1 '
b1 0
b1 1
b1110 c
b11 _
1!
#170000
0!
#175000
b101 (
b101 /
b101 P
b1100 _
b101 N
b1111 c
1!
#180000
0!
#185000
b11 '
b11 0
b11 1
b10000 c
b100 _
1!
#190000
0!
#195000
b100000011 (
b100000011 /
b100000011 P
b101 _
b100000011 7
b11 X
b10001 c
1!
#200000
0!
#205000
b0 '
b0 0
b0 1
b10010 c
b110 _
1!
#210000
0!
#215000
b101 (
b101 /
b101 P
b111 _
b10011 c
1!
#220000
0!
#225000
b110 (
b110 /
b110 P
b11 '
b11 0
b11 1
b10100 c
b0 _
b110 N
1!
#230000
0!
#235000
b10010000 '
b10010000 0
b10010000 1
b1 _
b10101 c
1!
#240000
0!
#245000
b1001 6
b0 4
b10110 c
b10 _
b10010000 V
1!
#250000
0!
#255000
b111 (
b111 /
b111 P
b1110 _
b111 N
b10111 c
1!
#260000
0!
#265000
b1 '
b1 0
b1 1
b11000 c
b11 _
1!
#270000
0!
#275000
b1000 (
b1000 /
b1000 P
b1100 _
b1000 N
b11001 c
1!
#280000
0!
#285000
b11 '
b11 0
b11 1
b11010 c
b100 _
1!
#290000
0!
#295000
b100000011 (
b100000011 /
b100000011 P
b101 _
b11011 c
1!
#300000
0!
#305000
b0 '
b0 0
b0 1
b11100 c
b110 _
1%
b1 &
b1 .
b1 S
1!
#310000
0!
#315000
b1000 (
b1000 /
b1000 P
b111 _
0%
b11101 c
1!
#320000
0!
#325000
b1001 (
b1001 /
b1001 P
b11 '
b11 0
b11 1
b11110 c
b0 _
b1001 N
1!
#330000
0!
#335000
b100001 '
b100001 0
b100001 1
b1 _
b11111 c
1!
#340000
0!
#345000
b10 6
b1 4
b100000 c
b10 _
b100001 V
1!
#350000
0!
#355000
b101 _
b100001 c
1!
#360000
0!
#365000
b100010 c
b111 _
b1 R
1!
#370000
0!
#375000
b1010 (
b1010 /
b1010 P
b0 _
b1010 N
b100011 c
1!
#380000
0!
#385000
b10010000 '
b10010000 0
b10010000 1
b100100 c
b1 _
1!
#390000
0!
#395000
b1001 6
b0 4
b10 _
b10010000 V
b100101 c
1!
#400000
0!
#405000
b1011 (
b1011 /
b1011 P
b100110 c
b1110 _
b1011 N
1!
#410000
0!
#415000
b1 '
b1 0
b1 1
b11 _
b100111 c
1!
#420000
0!
#425000
b1100 (
b1100 /
b1100 P
b101000 c
b1100 _
b1100 N
1!
#430000
0!
#435000
b10 '
b10 0
b10 1
b100 _
b101001 c
1!
#440000
0!
#445000
b100000010 (
b100000010 /
b100000010 P
b101010 c
b101 _
b100000010 7
b10 X
1!
#450000
0!
#455000
b1 '
b1 0
b1 1
b110 _
1%
b101011 c
1!
#460000
0!
#465000
b1100 (
b1100 /
b1100 P
b101100 c
b111 _
0%
1!
#470000
0!
#475000
b1101 (
b1101 /
b1101 P
b10 '
b10 0
b10 1
b0 _
b1101 N
b101101 c
1!
#480000
0!
#485000
b10100010 '
b10100010 0
b10100010 1
b101110 c
b1 _
1!
#490000
0!
#495000
b1010 6
b10 4
b10 _
b10100010 V
b101111 c
1!
#500000
0!
#505000
b1110 (
b1110 /
b1110 P
b110000 c
b1110 _
b1110 N
1!
#510000
0!
#515000
b1 '
b1 0
b1 1
b11 _
b110001 c
1!
#520000
0!
#525000
b1111 (
b1111 /
b1111 P
b110010 c
b1100 _
b1111 N
1!
#530000
0!
#535000
b100 _
b110011 c
1!
#540000
0!
#545000
b100000001 (
b100000001 /
b100000001 P
b110100 c
b101 _
b100000001 7
b1 X
1!
#550000
0!
#555000
b10 '
b10 0
b10 1
b110 _
b110101 c
1!
#560000
0!
#565000
b1111 (
b1111 /
b1111 P
b110110 c
b111 _
1!
#570000
0!
#575000
b10000 (
b10000 /
b10000 P
b1 '
b1 0
b1 1
b0 _
b10000 N
b110111 c
1!
#580000
0!
#585000
b1110011 '
b1110011 0
b1110011 1
b111000 c
b1 _
1!
#590000
0!
#595000
b111 6
b11 4
b10 _
b1110011 V
b111001 c
1!
#600000
0!
#605000
b10001 (
b10001 /
b10001 P
b111010 c
b1110 _
b10001 N
1!
#610000
0!
#615000
b1 '
b1 0
b1 1
b11 _
b111011 c
1!
#620000
0!
#625000
b111100 c
b101 _
1!
#630000
0!
#635000
b111 _
b1 Q
b111101 c
1!
#640000
0!
#645000
b10010 (
b10010 /
b10010 P
b111110 c
b0 _
b10010 N
1!
#650000
0!
#655000
b101011 '
b101011 0
b101011 1
b1 _
b111111 c
1!
#660000
0!
#665000
b10 6
b10 5
b1000000 c
b10 _
b101011 V
1!
#670000
0!
#675000
b101 _
b1000001 c
1!
#680000
0!
#685000
b1000010 c
b111 _
b11 R
1!
#690000
0!
#695000
b10011 (
b10011 /
b10011 P
b0 _
b10011 N
b1000011 c
1!
#700000
0!
#705000
b10100011 '
b10100011 0
b10100011 1
b1000100 c
b1 _
1!
#710000
0!
#715000
b1010 6
b0 5
b10 _
b10100011 V
b1000101 c
1!
#720000
0!
#725000
b10100 (
b10100 /
b10100 P
b1000110 c
b1110 _
b10100 N
1!
#730000
0!
#735000
b1 '
b1 0
b1 1
b11 _
b1000111 c
1!
#740000
0!
#745000
b10101 (
b10101 /
b10101 P
b1001000 c
b1100 _
b10101 N
1!
#750000
0!
#755000
b0 '
b0 0
b0 1
b100 _
b1001001 c
1!
#760000
0!
#765000
b100000000 (
b100000000 /
b100000000 P
b1001010 c
b101 _
b100000000 7
b0 X
1!
#770000
0!
#775000
b1010 '
b1010 0
b1010 1
b110 _
b1001011 c
1!
#780000
0!
#785000
b10101 (
b10101 /
b10101 P
b1001100 c
b111 _
1!
#790000
0!
#795000
b10110 (
b10110 /
b10110 P
b0 '
b0 0
b0 1
b0 _
b10110 N
b1001101 c
1!
#800000
0!
#805000
b111110 '
b111110 0
b111110 1
b1001110 c
b1 _
1!
#810000
0!
#815000
b11 6
b11 5
b10 4
b10 _
b111110 V
b1001111 c
1!
#820000
0!
#825000
b1010000 c
b101 _
1!
#830000
0!
#835000
b111 _
b111 R
b1010001 c
1!
#840000
0!
#845000
b10111 (
b10111 /
b10111 P
b1010010 c
b0 _
b10111 N
1!
#850000
0!
#855000
b10010010 '
b10010010 0
b10010010 1
b1 _
b1010011 c
1!
#860000
0!
#865000
b1001 6
b0 5
b1010100 c
b10 _
b10010010 V
1!
#870000
0!
#875000
b11000 (
b11000 /
b11000 P
b1110 _
b11000 N
b1010101 c
1!
#880000
0!
#885000
b1 '
b1 0
b1 1
b1010110 c
b11 _
1!
#890000
0!
#895000
b11001 (
b11001 /
b11001 P
b1100 _
b11001 N
b1010111 c
1!
#900000
0!
#905000
b1011000 c
b100 _
1!
#910000
0!
#915000
b100000001 (
b100000001 /
b100000001 P
b101 _
b100000001 7
b1 X
b1011001 c
1!
#920000
0!
#925000
b10 '
b10 0
b10 1
b1011010 c
b110 _
1%
b11 &
b11 .
b11 S
1!
#930000
0!
#935000
b11001 (
b11001 /
b11001 P
b111 _
0%
b1011011 c
1!
#940000
0!
#945000
b11010 (
b11010 /
b11010 P
b1 '
b1 0
b1 1
b1011100 c
b0 _
b11010 N
1!
#950000
0!
#955000
b11010001 '
b11010001 0
b11010001 1
b1 _
b1011101 c
1!
#960000
0!
#965000
b1101 6
b1 4
b1011110 c
b10 _
b11010001 V
1!
#970000
0!
#975000
b11011 (
b11011 /
b11011 P
b1110 _
b11011 N
b1011111 c
1!
#980000
0!
#985000
b0 '
b0 0
b0 1
b1100000 c
b11 _
1!
#990000
0!
#995000
b11100 (
b11100 /
b11100 P
b1100 _
b11100 N
b1 7
b0 2
b0 W
b1100001 c
1!
#1000000
0!
#1005000
b100000 '
b100000 0
b100000 1
b1100010 c
b100 _
1!
#1010000
0!
#1015000
b101 _
b100000 7
b100000 X
b1100011 c
1!
#1020000
0!
#1025000
b1100100 c
b111 _
1!
#1030000
0!
#1035000
b0 _
b1100101 c
1!
#1040000
0!
#1045000
b1100110 c
b1 _
1!
#1050000
0!
#1055000
b10 6
b0 4
b10 _
b100000 V
b1100111 c
1!
#1060000
0!
#1065000
b1101000 c
b101 _
1!
#1070000
0!
#1075000
b111 _
b10 R
b1101001 c
1!
#1080000
0!
#1085000
b11101 (
b11101 /
b11101 P
b1101010 c
b0 _
b11101 N
1!
#1090000
0!
#1095000
b11010000 '
b11010000 0
b11010000 1
b1 _
b1101011 c
1!
#1100000
0!
#1105000
b1101 6
b1101100 c
b10 _
b11010000 V
1!
#1110000
0!
#1115000
b11110 (
b11110 /
b11110 P
b1110 _
b11110 N
b1101101 c
1!
#1120000
0!
#1125000
b0 '
b0 0
b0 1
b1101110 c
b11 _
1!
#1130000
0!
#1135000
b11111 (
b11111 /
b11111 P
b1100 _
b11111 N
b1101111 c
1!
#1140000
0!
#1145000
b1110000 c
b100 _
1!
#1150000
0!
#1155000
b101 _
b0 7
b0 X
b1110001 c
1!
#1160000
0!
