src/core.sv
module core(
  input clk_i,
  input rst_i,
  // Работа с внешними устройствами
  input irq_i,          // Сигнал прерывания
  input [7:0] io_data_i,// Данные от устройств ввода
  output reg [7:0] io_data_o,// Данные для устройств вывода
  output reg [7:0] io_addr_o,// Адрес устройства ввода/вывода
  output reg io_we_o,   // Сигнал записи в устройство вывода
  // Интерфейс памяти
  output reg [15:0] address_o,  
  input [7:0] data_i,
  output reg we_i,              
  output reg [7:0] data_o
);

  // Состояния конечного автомата
  localparam IDLE_S     = 4'd0;
  localparam FETCH_S    = 4'd1;
  localparam DECODE_S   = 4'd2;
  localparam FETCH2_S   = 4'd3;
  localparam FETCH3_S   = 4'd4;
  localparam EXEC_S     = 4'd5;
  localparam MEM_S      = 4'd6;
  localparam WB_S       = 4'd7;
  localparam INT_SAVE_S = 4'd8;  // Сохранение состояния при прерывании
  localparam INT_JUMP_S = 4'd9;  // Переход к обработчику
  localparam HALT_S     = 4'd10; // Состояние останова
  localparam V_S        = 4'd11;
  localparam V2_S = 4'd12;

  // Определение битов флагов
  localparam FLAG_Z     = 0; // Zero
  localparam FLAG_C     = 1; // Carry
  localparam FLAG_V     = 2; // Overflow
  localparam FLAG_S     = 3; // Sign
  localparam FLAG_IF    = 4; // Interrupt Flag

  // Адрес вектора прерываний
  localparam IVT_ADDR   = 16'hFFFE;

  // Регистры процессора
  reg [3:0] state;
  reg [7:0] RF [0:3];  // Регистровый файл (A=0, B=1, C=2, D=3)
  reg [15:0] PC;       // Счетчик команд
  reg [15:0] SP;       // Указатель стека
  reg [7:0] flags;     // Регистр флагов
  
  // Регистры для хранения инструкций
  reg [7:0] instruction;
  reg [7:0] instruction_2nd_byte;
  reg [7:0] instruction_3rd_byte;
  
  // Временные регистры
  reg [7:0] alu_result;
  reg [8:0] alu_result_ext; // 9 бит для учета переноса
  reg [15:0] int_save_pc;   // Для сохранения PC при прерывании
  reg [7:0] int_save_flags; // Для сохранения флагов при прерывании
  
  // Комбинационные сигналы
  wire [3:0] opcode = instruction[7:4];
  wire [1:0] reg1 = instruction[3:2];
  wire [1:0] reg2 = instruction[1:0];
  wire [7:0] imm8 = instruction_2nd_byte;
  wire [15:0] addr16 = {instruction_2nd_byte, instruction_3rd_byte};

  // Логика следующего состояния
  always @(posedge clk_i or posedge rst_i) begin
    if (rst_i) begin
      state <= IDLE_S;
      PC <= 16'h0000;
      SP <= 16'hFFFF;
      flags <= 8'b00000000;
      we_i <= 1'b0;
      io_we_o <= 1'b0;
      RF[0] <= '0;
      RF[1] <= '0;
      RF[2] <= '0;
      RF[3] <= '0;
    end else begin
      case (state)
        IDLE_S: begin
          if (!halt) state <= FETCH_S;
        end
        
        FETCH_S: begin
          instruction <= data_i;
          state <= DECODE_S;
        end
        
        DECODE_S: begin
          case (opcode)
            // 2-байтовые команды
            4'h7, 4'h8, 4'hB, 4'hC: begin
              PC <= PC + 1;
              state <= V_S;
              
            end
            // 3-байтовые команды
            4'h9, 4'hA, 4'hD: begin
              PC <= PC + 1;
              state <= V_S;
            end
            // 1-байтовые команды
            default: state <= EXEC_S;
          endcase
        end
        
        V_S: state <= FETCH2_S;

        FETCH2_S: begin
          instruction_2nd_byte <= data_i;
          case (opcode)
            // 3-байтовые команды
            4'h9, 4'hA, 4'hD: begin
              PC <= PC + 1;
              state <= V2_S;
            end
            // 2-байтовые команды
            default: state <= EXEC_S;
          endcase
        end
        
        V2_S: state <= FETCH3_S;

        FETCH3_S: begin
          instruction_3rd_byte <= data_i;
          state <= EXEC_S;
        end
        
        EXEC_S: begin
          // Выполнение операции
          case (opcode)
            // MOV R1, R2
            4'h1: alu_result <= RF[reg2];
            
            // ADD R1, R2
            4'h2: alu_result_ext <= RF[reg1] + RF[reg2];
            
            // SUB R1, R2
            4'h3: alu_result_ext <= RF[reg1] - RF[reg2];
            
            // AND R1, R2
            4'h4: alu_result <= RF[reg1] & RF[reg2];
            
            // OR R1, R2
            4'h5: alu_result <= RF[reg1] | RF[reg2];
            
            // XOR R1, R2
            4'h6: alu_result <= RF[reg1] ^ RF[reg2];
            
            // MOV R, IMM8
            4'h7: alu_result <= imm8;
            
            // ADD R, IMM8
            4'h8: alu_result_ext <= RF[reg1] + imm8;
            
            // MOV [ADDR16], R
            4'h9: begin
              address_o <= addr16;
              data_o <= RF[reg2];
              we_i <= 1'b1;
            end
            
            // MOV R, [ADDR16]
            4'hA: begin
              address_o <= addr16;
            end
            
            // IN R, PORT8
            4'hB: begin
              io_addr_o <= imm8;
              io_we_o <= 1'b0;
            end
            
            // OUT PORT8, R
            4'hC: begin
              io_addr_o <= imm8;
              io_data_o <= RF[reg1];
              io_we_o <= 1'b1;
            end
            
            // JMP/JZ/JC ADDR16
            4'hD: begin
              case (instruction[3:0])
                4'd0: PC <= addr16; // JMP
                4'd1: if (flags[FLAG_Z]) PC <= addr16; // JZ
                4'd2: if (flags[FLAG_C]) PC <= addr16; // JC
              endcase
            end
            
            // EI/DI
            4'hE: begin
              case (instruction[3:0])
                4'h0: flags[FLAG_IF] <= 1'b1; // EI
                4'h1: flags[FLAG_IF] <= 1'b0; // DI
                4'hF: begin /* HALT - обрабатывается отдельно */ end
              endcase
            end
          endcase
          
          // Переход в следующее состояние
          if (opcode == 4'h9 || opcode == 4'hA || opcode == 4'hB || opcode == 4'hC) begin
            state <= MEM_S;
          end else begin
            state <= WB_S;
          end
        end
        
        MEM_S: begin
          we_i <= 1'b0;
          io_we_o <= 1'b0;
          state <= WB_S;
        end
        
        WB_S: begin
          case (opcode)
            // MOV R1, R2
            4'h1: RF[reg1] <= alu_result;
            
            // ADD R1, R2
            4'h2: begin
              RF[reg1] <= alu_result_ext[7:0];
              flags[FLAG_Z] <= (alu_result_ext[7:0] == 8'b0);
              flags[FLAG_C] <= alu_result_ext[8];
              flags[FLAG_V] <= (RF[reg1][7] == RF[reg2][7]) && 
                              (alu_result_ext[7] != RF[reg1][7]);
              flags[FLAG_S] <= alu_result_ext[7];
            end
            
            // SUB R1, R2
            4'h3: begin
              RF[reg1] <= alu_result_ext[7:0];
              flags[FLAG_Z] <= (alu_result_ext[7:0] == 8'b0);
              flags[FLAG_C] <= alu_result_ext[8];
              flags[FLAG_V] <= (RF[reg1][7] != RF[reg2][7]) && 
                              (alu_result_ext[7] != RF[reg1][7]);
              flags[FLAG_S] <= alu_result_ext[7];
            end
            
            // AND/OR/XOR R1, R2
            4'h4, 4'h5, 4'h6: begin
              RF[reg1] <= alu_result;
              flags[FLAG_Z] <= (alu_result == 8'b0);
              flags[FLAG_S] <= alu_result[7];
              flags[FLAG_C] <= 1'b0;
              flags[FLAG_V] <= 1'b0;
            end
            
            // MOV R, IMM8
            4'h7: RF[reg2] <= alu_result;
            
            // ADD R, IMM8
            4'h8: begin
              RF[reg1] <= alu_result_ext[7:0];
              flags[FLAG_Z] <= (alu_result_ext[7:0] == 8'b0);
              flags[FLAG_C] <= alu_result_ext[8];
              flags[FLAG_V] <= (RF[reg1][7] == imm8[7]) && 
                              (alu_result_ext[7] != RF[reg1][7]);
              flags[FLAG_S] <= alu_result_ext[7];
            end
            
            // MOV R, [ADDR16]
            4'hA: RF[reg2] <= data_i;
            
            // IN R, PORT8
            4'hB: RF[reg1] <= io_data_i;
          endcase
          
          // Обновление PC для всех команд кроме JMP/JZ/JC
          if (opcode != 4'hD) begin
            PC <= PC + 1;
          end
          
          state <= IDLE_S;
        end
        
        // Обработка прерываний
        INT_SAVE_S: begin
          // Сохраняем PC в стек
          SP <= SP - 2;
          address_o <= SP;
          data_o <= int_save_pc[7:0];
          we_i <= 1'b1;
          state <= INT_JUMP_S;
        end
        
        INT_JUMP_S: begin
          // Сохраняем флаги в стек и переходим к обработчику
          we_i <= 1'b0;
          SP <= SP - 2;
          address_o <= SP;
          data_o <= int_save_flags;
          we_i <= 1'b1;
          PC <= IVT_ADDR;
          flags[FLAG_IF] <= 1'b0; // Запрещаем прерывания
          state <= FETCH_S;
        end
        
        HALT_S: begin
          // Останов процессора
          if (irq_i && flags[FLAG_IF]) begin
            state <= INT_SAVE_S;
          end
        end
      endcase
    end
  end

  // Логика прерываний
  always @(posedge clk_i) begin
    if (irq_i && flags[FLAG_IF] && state == WB_S && !halt) begin
      int_save_pc <= PC;
      int_save_flags <= flags;
      state <= INT_SAVE_S;
    end
  end

  // Останов процессора
  reg halt;
  always @(posedge clk_i) begin
    if (rst_i) begin
      halt <= 1'b0;
    end else if (state == EXEC_S && opcode == 4'hE && instruction[3:0] == 4'hF) begin
      halt <= 1'b1;
      state <= HALT_S;
    end
  end

  // Управление адресом памяти
  always @(*) begin
    case (state)
      //V_S, V2_S, FETCH_S, FETCH2_S, FETCH3_S: address_o <= PC;
      EXEC_S: begin
        case (opcode)
          4'h9:  address_o <= addr16;
          4'hA: address_o <= addr16; // Для операций с памятью
          default: address_o <= PC;
        endcase
      end
      MEM_S: begin
      case (opcode)
          4'h9:  address_o <= addr16;
          4'hA: address_o <= addr16; // Для операций с памятью
          default: address_o <= PC;
        endcase
      end
      INT_JUMP_S: address_o <= IVT_ADDR;
      default: address_o <= PC;
    endcase
  end
endmodule

src/ram.sv
module ram (
  input clk_i,
  input rst_i,
  // A\D line
  input [15:0] address_i,
  input [7:0] data_i,
  input we_i,
  output logic [7:0] data_o
);

logic [7:0] mem [65536];

always_ff @( posedge clk_i ) begin
  if (we_i) mem [address_i] <= data_i;
end

always_ff @(posedge clk_i) begin
  data_o <= mem [address_i]; 
end
  
endmodule

src/top.sv
module top (
  input clk_i,
  input rst_i
);

wire [15:0] ram_address_line;
wire [7:0] ram_data_to_r_line;
wire [7:0] ram_data_from_r_line;
wire ram_we;

wire irq = 0;
wire [7:0] io_data_i;

ram u0(
  .clk_i         (clk_i),
  .rst_i         (rst_i),
  // A\D line
  .address_i     (ram_address_line),
  .data_i        (ram_data_to_r_line),
  .we_i          (ram_we),
  .data_o        (ram_data_from_r_line)
);

core u1(
  .clk_i         (clk_i),
  .rst_i         (rst_i),
  // A\D line
  .address_o     (ram_address_line),  
  .data_i        (ram_data_from_r_line),
  .we_i          (ram_we),              
  .data_o        (ram_data_to_r_line),
 // IO A\D line
  .irq_i         (irq),          
  .io_data_i     (io_data_i)     
);

  
endmodule

tb/tb_processor.sv
`timescale 1ns / 1ps

module tb_processor();

// Тактовый сигнал и сброс
reg clk = 0;
reg rst = 0;

// Подключение верхнего модуля
top dut (
    .clk_i(clk),
    .rst_i(rst)
);

always #5 clk = ~clk;

// ==============================================
// ТЕСТ 1: Базовые арифметические операции
// ==============================================
initial begin
   $dumpfile("dump.vcd"); $dumpvars;
   /*
   //$monitor(" Registers: A=%h, B=%h, C=%h, D=%h, 0=%h, 1=%h, 2=%h, 3=%h", 
                 dut.u1.RF[0], dut.u1.RF[1], dut.u1.RF[2], dut.u1.RF[3], dut.u0.mem[16'h0100], dut.u0.mem[16'h0101], dut.u0.mem[16'h0102], dut.u0.mem[16'h0103]);
    rst = 1'b1;
    // Инициализация памяти для теста арифметики
    $readmemh("out.bin.hex", dut.u0.mem);
    #25
    rst = 1'b0;
    @(dut.u1.halt);
    #10
    $display(" Registers: A=%h, B=%h, C=%h, D=%h", 
                 dut.u1.RF[0], dut.u1.RF[1], dut.u1.RF[2], dut.u1.RF[3]);
    $display("  Flags: Z=%b, C=%b, V=%b, S=%b, IF=%b",
                 dut.u1.flags[0], dut.u1.flags[1], dut.u1.flags[2], 
                 dut.u1.flags[3], dut.u1.flags[4]);
    // Проверка результатов
    if (dut.u1.RF[0] != 8'h10 || dut.u1.RF[1] != 8'h02 || 
        dut.u1.flags[0] != 1'b0 || dut.u1.flags[1] != 1'b1) begin
        $display("TEST 1 FAILED!");
    end else begin
        $display("TEST 1 PASSED!");
    end
    #10
    rst = 1'b1;
    // Инициализация памяти для теста арифметики
    $readmemh("out2.bin.hex", dut.u0.mem);
    #25
    rst = 1'b0;
    @(dut.u1.halt);
    #10
    if (dut.u1.RF[1] != 8'h05 || dut.u0.mem[16'h0100] != 8'h05) begin
        $display("TEST 2 FAILED!");
    end else begin
        $display("TEST 2 PASSED!");
    end

    */
    #10
    rst = 1'b1;
    // Инициализация памяти для теста арифметики
    $readmemh("out3.bin.hex", dut.u0.mem);
    #25
    rst = 1'b0;
    @(dut.u1.halt);
    $display(" Registers: A=%h, B=%h, C=%h, D=%h", 
                 dut.u1.RF[0], dut.u1.RF[1], dut.u1.RF[2], dut.u1.RF[3]);
    $display("  Flags: Z=%b, C=%b, V=%b, S=%b, IF=%b",
                 dut.u1.flags[0], dut.u1.flags[1], dut.u1.flags[2], 
                 dut.u1.flags[3], dut.u1.flags[4]);
    $display("All tests completed");
    $finish;
end

endmodule

dump.vcd
$date
	Sun Mar 30 04:28:07 2025
$end
$version
	Icarus Verilog
$end
$timescale
	1ps
$end
$scope module tb_processor $end
$var reg 1 ! clk $end
$var reg 1 " rst $end
$scope module dut $end
$var wire 1 ! clk_i $end
$var wire 8 # io_data_i [7:0] $end
$var wire 1 $ irq $end
$var wire 1 " rst_i $end
$var wire 1 % ram_we $end
$var wire 8 & ram_data_to_r_line [7:0] $end
$var wire 8 ' ram_data_from_r_line [7:0] $end
$var wire 16 ( ram_address_line [15:0] $end
$scope module u0 $end
$var wire 1 ! clk_i $end
$var wire 1 " rst_i $end
$var wire 1 % we_i $end
$var wire 8 ) data_i [7:0] $end
$var wire 16 * address_i [15:0] $end
$var reg 8 + data_o [7:0] $end
$upscope $end
$scope module u1 $end
$var wire 1 ! clk_i $end
$var wire 8 , data_i [7:0] $end
$var wire 8 - imm8 [7:0] $end
$var wire 8 . io_data_i [7:0] $end
$var wire 1 $ irq_i $end
$var wire 1 " rst_i $end
$var wire 2 / reg2 [1:0] $end
$var wire 2 0 reg1 [1:0] $end
$var wire 4 1 opcode [3:0] $end
$var wire 16 2 addr16 [15:0] $end
$var parameter 4 3 DECODE_S $end
$var parameter 4 4 EXEC_S $end
$var parameter 4 5 FETCH2_S $end
$var parameter 4 6 FETCH3_S $end
$var parameter 4 7 FETCH_S $end
$var parameter 32 8 FLAG_C $end
$var parameter 32 9 FLAG_IF $end
$var parameter 32 : FLAG_S $end
$var parameter 32 ; FLAG_V $end
$var parameter 32 < FLAG_Z $end
$var parameter 4 = HALT_S $end
$var parameter 4 > IDLE_S $end
$var parameter 4 ? INT_JUMP_S $end
$var parameter 4 @ INT_SAVE_S $end
$var parameter 16 A IVT_ADDR $end
$var parameter 4 B MEM_S $end
$var parameter 4 C V2_S $end
$var parameter 4 D V_S $end
$var parameter 4 E WB_S $end
$var reg 16 F PC [15:0] $end
$var reg 16 G SP [15:0] $end
$var reg 16 H address_o [15:0] $end
$var reg 8 I alu_result [7:0] $end
$var reg 9 J alu_result_ext [8:0] $end
$var reg 8 K data_o [7:0] $end
$var reg 8 L flags [7:0] $end
$var reg 1 M halt $end
$var reg 8 N instruction [7:0] $end
$var reg 8 O instruction_2nd_byte [7:0] $end
$var reg 8 P instruction_3rd_byte [7:0] $end
$var reg 8 Q int_save_flags [7:0] $end
$var reg 16 R int_save_pc [15:0] $end
$var reg 8 S io_addr_o [7:0] $end
$var reg 8 T io_data_o [7:0] $end
$var reg 1 U io_we_o $end
$var reg 4 V state [3:0] $end
$var reg 1 % we_i $end
$upscope $end
$upscope $end
$upscope $end
$enddefinitions $end
$comment Show the parameter values. $end
$dumpall
b111 E
b1011 D
b1100 C
b110 B
b1111111111111110 A
b1000 @
b1001 ?
b0 >
b1010 =
b0 <
b10 ;
b11 :
b100 9
b1 8
b1 7
b100 6
b11 5
b101 4
b10 3
$end
#0
$dumpvars
bx V
xU
bx T
bx S
bx R
bx Q
bx P
bx O
bx N
xM
bx L
bx K
bx J
bx I
bx H
bx G
bx F
bx 2
bx 1
bx 0
bx /
bz .
bx -
bx ,
bx +
bx *
bx )
bx (
bx '
bx &
x%
0$
bz #
0"
0!
$end
#5000
1!
#10000
b0 (
b0 *
b0 H
0U
0%
b0 L
b1111111111111111 G
b0 F
b0 V
0!
1"
#15000
0M
b10100000 '
b10100000 +
b10100000 ,
1!
#20000
0!
#25000
1!
#30000
0!
#35000
b1 V
1!
0"
#40000
0!
#45000
b1010 1
b0 0
b0 /
b10 V
b10100000 N
1!
#50000
0!
#55000
b1 (
b1 *
b1 H
b1011 V
b1 F
1!
#60000
0!
#65000
b1 '
b1 +
b1 ,
b11 V
1!
#70000
0!
#75000
b10 (
b10 *
b10 H
b1100 V
b10 F
b1xxxxxxxx 2
b1 -
b1 O
1!
#80000
0!
#85000
b10 '
b10 +
b10 ,
b100 V
1!
#90000
0!
#95000
b100000010 (
b100000010 *
b100000010 H
b101 V
b100000010 2
b10 P
1!
#100000
0!
#105000
b1 '
b1 +
b1 ,
b110 V
1!
#110000
0!
#115000
b10 (
b10 *
b10 H
b111 V
1!
#120000
0!
#125000
b11 (
b11 *
b11 H
b10 '
b10 +
b10 ,
b0 V
b11 F
1!
#130000
0!
#135000
b10100001 '
b10100001 +
b10100001 ,
b1 V
1!
#140000
0!
#145000
b1 /
b10 V
b10100001 N
1!
#150000
0!
#155000
b100 (
b100 *
b100 H
b1011 V
b100 F
1!
#160000
0!
#165000
b1 '
b1 +
b1 ,
b11 V
1!
#170000
0!
#175000
b101 (
b101 *
b101 H
b1100 V
b101 F
1!
#180000
0!
#185000
b11 '
b11 +
b11 ,
b100 V
1!
#190000
0!
#195000
b100000011 (
b100000011 *
b100000011 H
b101 V
b100000011 2
b11 P
1!
#200000
0!
#205000
b1 '
b1 +
b1 ,
b110 V
1!
#210000
0!
#215000
b101 (
b101 *
b101 H
b111 V
1!
#220000
0!
#225000
b110 (
b110 *
b110 H
b11 '
b11 +
b11 ,
b0 V
b110 F
1!
#230000
0!
#235000
b10010000 '
b10010000 +
b10010000 ,
b1 V
1!
#240000
0!
#245000
b1001 1
b0 /
b10 V
b10010000 N
1!
#250000
0!
#255000
b111 (
b111 *
b111 H
b1011 V
b111 F
1!
#260000
0!
#265000
b1 '
b1 +
b1 ,
b11 V
1!
#270000
0!
#275000
b1000 (
b1000 *
b1000 H
b1100 V
b1000 F
1!
#280000
0!
#285000
b11 '
b11 +
b11 ,
b100 V
1!
#290000
0!
#295000
b100000011 (
b100000011 *
b100000011 H
b101 V
1!
#300000
0!
#305000
b1 '
b1 +
b1 ,
b110 V
1%
b1 &
b1 )
b1 K
1!
#310000
0!
#315000
b1000 (
b1000 *
b1000 H
b111 V
0%
1!
#320000
0!
#325000
b1001 (
b1001 *
b1001 H
b11 '
b11 +
b11 ,
b0 V
b1001 F
1!
#330000
0!
#335000
b100001 '
b100001 +
b100001 ,
b1 V
1!
#340000
0!
#345000
b10 1
b1 /
b10 V
b100001 N
1!
#350000
0!
#355000
b101 V
1!
#360000
0!
#365000
b111 V
b10 J
1!
#370000
0!
#375000
b1010 (
b1010 *
b1010 H
b0 V
b1010 F
1!
#380000
0!
#385000
b10010000 '
b10010000 +
b10010000 ,
b1 V
1!
#390000
0!
#395000
b1001 1
b0 /
b10 V
b10010000 N
1!
#400000
0!
#405000
b1011 (
b1011 *
b1011 H
b1011 V
b1011 F
1!
#410000
0!
#415000
b1 '
b1 +
b1 ,
b11 V
1!
#420000
0!
#425000
b1100 (
b1100 *
b1100 H
b1100 V
b1100 F
1!
#430000
0!
#435000
b10 '
b10 +
b10 ,
b100 V
1!
#440000
0!
#445000
b100000010 (
b100000010 *
b100000010 H
b101 V
b100000010 2
b10 P
1!
#450000
0!
#455000
b1 '
b1 +
b1 ,
b110 V
1%
b10 &
b10 )
b10 K
1!
#460000
0!
#465000
b1100 (
b1100 *
b1100 H
b111 V
0%
1!
#470000
0!
#475000
b1101 (
b1101 *
b1101 H
b10 '
b10 +
b10 ,
b0 V
b1101 F
1!
#480000
0!
#485000
b10100010 '
b10100010 +
b10100010 ,
b1 V
1!
#490000
0!
#495000
b1010 1
b10 /
b10 V
b10100010 N
1!
#500000
0!
#505000
b1110 (
b1110 *
b1110 H
b1011 V
b1110 F
1!
#510000
0!
#515000
b1 '
b1 +
b1 ,
b11 V
1!
#520000
0!
#525000
b1111 (
b1111 *
b1111 H
b1100 V
b1111 F
1!
#530000
0!
#535000
b100 V
1!
#540000
0!
#545000
b100000001 (
b100000001 *
b100000001 H
b101 V
b100000001 2
b1 P
1!
#550000
0!
#555000
b10 '
b10 +
b10 ,
b110 V
1!
#560000
0!
#565000
b1111 (
b1111 *
b1111 H
b111 V
1!
#570000
0!
#575000
b10000 (
b10000 *
b10000 H
b1 '
b1 +
b1 ,
b0 V
b10000 F
1!
#580000
0!
#585000
b1110011 '
b1110011 +
b1110011 ,
b1 V
1!
#590000
0!
#595000
b111 1
b11 /
b10 V
b1110011 N
1!
#600000
0!
#605000
b10001 (
b10001 *
b10001 H
b1011 V
b10001 F
1!
#610000
0!
#615000
b1 '
b1 +
b1 ,
b11 V
1!
#620000
0!
#625000
b101 V
1!
#630000
0!
#635000
b111 V
b1 I
1!
#640000
0!
#645000
b10010 (
b10010 *
b10010 H
b0 V
b10010 F
1!
#650000
0!
#655000
b101011 '
b101011 +
b101011 ,
b1 V
1!
#660000
0!
#665000
b10 1
b10 0
b10 V
b101011 N
1!
#670000
0!
#675000
b101 V
1!
#680000
0!
#685000
b111 V
b11 J
1!
#690000
0!
#695000
b10011 (
b10011 *
b10011 H
b0 V
b10011 F
1!
#700000
0!
#705000
b10100011 '
b10100011 +
b10100011 ,
b1 V
1!
#710000
0!
#715000
b1010 1
b0 0
b10 V
b10100011 N
1!
#720000
0!
#725000
b10100 (
b10100 *
b10100 H
b1011 V
b10100 F
1!
#730000
0!
#735000
b1 '
b1 +
b1 ,
b11 V
1!
#740000
0!
#745000
b10101 (
b10101 *
b10101 H
b1100 V
b10101 F
1!
#750000
0!
#755000
b0 '
b0 +
b0 ,
b100 V
1!
#760000
0!
#765000
b100000000 (
b100000000 *
b100000000 H
b101 V
b100000000 2
b0 P
1!
#770000
0!
#775000
b1010 '
b1010 +
b1010 ,
b110 V
1!
#780000
0!
#785000
b10101 (
b10101 *
b10101 H
b111 V
1!
#790000
0!
#795000
b10110 (
b10110 *
b10110 H
b0 '
b0 +
b0 ,
b0 V
b10110 F
1!
#800000
0!
#805000
b111110 '
b111110 +
b111110 ,
b1 V
1!
#810000
0!
#815000
b11 1
b11 0
b10 /
b10 V
b111110 N
1!
#820000
0!
#825000
b101 V
1!
#830000
0!
#835000
b111 V
b111 J
1!
#840000
0!
#845000
b10111 (
b10111 *
b10111 H
b0 V
b10111 F
1!
#850000
0!
#855000
b10010010 '
b10010010 +
b10010010 ,
b1 V
1!
#860000
0!
#865000
b1001 1
b0 0
b10 V
b10010010 N
1!
#870000
0!
#875000
b11000 (
b11000 *
b11000 H
b1011 V
b11000 F
1!
#880000
0!
#885000
b1 '
b1 +
b1 ,
b11 V
1!
#890000
0!
#895000
b11001 (
b11001 *
b11001 H
b1100 V
b11001 F
1!
#900000
0!
#905000
b100 V
1!
#910000
0!
#915000
b100000001 (
b100000001 *
b100000001 H
b101 V
b100000001 2
b1 P
1!
#920000
0!
#925000
b10 '
b10 +
b10 ,
b110 V
1%
b11 &
b11 )
b11 K
1!
#930000
0!
#935000
b11001 (
b11001 *
b11001 H
b111 V
0%
1!
#940000
0!
#945000
b11010 (
b11010 *
b11010 H
b1 '
b1 +
b1 ,
b0 V
b11010 F
1!
#950000
0!
#955000
b11010001 '
b11010001 +
b11010001 ,
b1 V
1!
#960000
0!
#965000
b1101 1
b1 /
b10 V
b11010001 N
1!
#970000
0!
#975000
b11011 (
b11011 *
b11011 H
b1011 V
b11011 F
1!
#980000
0!
#985000
b0 '
b0 +
b0 ,
b11 V
1!
#990000
0!
#995000
b11100 (
b11100 *
b11100 H
b1100 V
b11100 F
b1 2
b0 -
b0 O
1!
#1000000
0!
#1005000
b100000 '
b100000 +
b100000 ,
b100 V
1!
#1010000
0!
#1015000
b101 V
b100000 2
b100000 P
1!
#1020000
0!
#1025000
b111 V
1!
#1030000
0!
#1035000
b0 V
1!
#1040000
0!
#1045000
b1 V
1!
#1050000
0!
#1055000
b10 1
b0 /
b10 V
b100000 N
1!
#1060000
0!
#1065000
b101 V
1!
#1070000
0!
#1075000
b111 V
b100 J
1!
#1080000
0!
#1085000
b11101 (
b11101 *
b11101 H
b0 V
b11101 F
1!
#1090000
0!
#1095000
b11010000 '
b11010000 +
b11010000 ,
b1 V
1!
#1100000
0!
#1105000
b1101 1
b10 V
b11010000 N
1!
#1110000
0!
#1115000
b11110 (
b11110 *
b11110 H
b1011 V
b11110 F
1!
#1120000
0!
#1125000
b0 '
b0 +
b0 ,
b11 V
1!
#1130000
0!
#1135000
b11111 (
b11111 *
b11111 H
b1100 V
b11111 F
1!
#1140000
0!
#1145000
b100 V
1!
#1150000
0!
#1155000
b101 V
b0 2
b0 P
1!
#1160000
0!
#1165000
b0 (
b0 *
b0 H
b111 V
b0 F
1!
#1170000
0!
#1175000
b10100000 '
b10100000 +
b10100000 ,
b0 V
1!
#1180000
0!
#1185000
b1 V
1!
#1190000
0!
#1195000
b1010 1
b10 V
b10100000 N
1!
#1200000
0!
#1205000
b1 (
b1 *
b1 H
b1011 V
b1 F
1!
#1210000
0!
#1215000
b1 '
b1 +
b1 ,
b11 V
1!
#1220000
0!
#1225000
b10 (
b10 *
b10 H
b1100 V
b10 F
b100000000 2
b1 -
b1 O
1!
#1230000
0!
#1235000
b10 '
b10 +
b10 ,
b100 V
1!
#1240000
0!
#1245000
b100000010 (
b100000010 *
b100000010 H
b101 V
b100000010 2
b10 P
1!
#1250000
0!
#1255000
b110 V
1!
#1260000
0!
#1265000
b10 (
b10 *
b10 H
b111 V
1!
#1270000
0!
#1275000
b11 (
b11 *
b11 H
b0 V
b11 F
1!
#1280000
0!
#1285000
b10100001 '
b10100001 +
b10100001 ,
b1 V
1!
#1290000
0!
#1295000
b1 /
b10 V
b10100001 N
1!
#1300000
0!
#1305000
b100 (
b100 *
b100 H
b1011 V
b100 F
1!
#1310000
0!
#1315000
b1 '
b1 +
b1 ,
b11 V
1!
#1320000
0!
#1325000
b101 (
b101 *
b101 H
b1100 V
b101 F
1!
#1330000
0!
#1335000
b11 '
b11 +
b11 ,
b100 V
1!
#1340000
0!
#1345000
b100000011 (
b100000011 *
b100000011 H
b101 V
b100000011 2
b11 P
1!
#1350000
0!
#1355000
b1 '
b1 +
b1 ,
b110 V
1!
#1360000
0!
#1365000
b101 (
b101 *
b101 H
b111 V
1!
#1370000
0!
#1375000
b110 (
b110 *
b110 H
b11 '
b11 +
b11 ,
b0 V
b110 F
1!
#1380000
0!
#1385000
b10010000 '
b10010000 +
b10010000 ,
b1 V
1!
#1390000
0!
#1395000
b1001 1
b0 /
b10 V
b10010000 N
1!
#1400000
0!
#1405000
b111 (
b111 *
b111 H
b1011 V
b111 F
1!
#1410000
0!
#1415000
b1 '
b1 +
b1 ,
b11 V
1!
#1420000
0!
#1425000
b1000 (
b1000 *
b1000 H
b1100 V
b1000 F
1!
#1430000
0!
#1435000
b11 '
b11 +
b11 ,
b100 V
1!
#1440000
0!
#1445000
b100000011 (
b100000011 *
b100000011 H
b101 V
1!
#1450000
0!
#1455000
b1 '
b1 +
b1 ,
b110 V
1%
b10 &
b10 )
b10 K
1!
#1460000
0!
#1465000
b1000 (
b1000 *
b1000 H
b111 V
0%
1!
#1470000
0!
#1475000
b1001 (
b1001 *
b1001 H
b11 '
b11 +
b11 ,
b0 V
b1001 F
1!
#1480000
0!
#1485000
b100001 '
b100001 +
b100001 ,
b1 V
1!
#1490000
0!
#1495000
b10 1
b1 /
b10 V
b100001 N
1!
#1500000
0!
#1505000
b101 V
1!
#1510000
0!
#1515000
b111 V
b11 J
1!
#1520000
0!
#1525000
b1010 (
b1010 *
b1010 H
b0 V
b1010 F
1!
#1530000
0!
#1535000
b10010000 '
b10010000 +
b10010000 ,
b1 V
1!
#1540000
0!
#1545000
b1001 1
b0 /
b10 V
b10010000 N
1!
#1550000
0!
#1555000
b1011 (
b1011 *
b1011 H
b1011 V
b1011 F
1!
#1560000
0!
#1565000
b1 '
b1 +
b1 ,
b11 V
1!
#1570000
0!
#1575000
b1100 (
b1100 *
b1100 H
b1100 V
b1100 F
1!
#1580000
0!
#1585000
b10 '
b10 +
b10 ,
b100 V
1!
#1590000
0!
#1595000
b100000010 (
b100000010 *
b100000010 H
b101 V
b100000010 2
b10 P
1!
#1600000
0!
#1605000
b110 V
1%
b11 &
b11 )
b11 K
1!
#1610000
0!
#1615000
b1100 (
b1100 *
b1100 H
b111 V
0%
1!
#1620000
0!
#1625000
b1101 (
b1101 *
b1101 H
b0 V
b1101 F
1!
#1630000
0!
#1635000
b10100010 '
b10100010 +
b10100010 ,
b1 V
1!
#1640000
0!
#1645000
b1010 1
b10 /
b10 V
b10100010 N
1!
#1650000
0!
#1655000
b1110 (
b1110 *
b1110 H
b1011 V
b1110 F
1!
#1660000
0!
#1665000
b1 '
b1 +
b1 ,
b11 V
1!
#1670000
0!
#1675000
b1111 (
b1111 *
b1111 H
b1100 V
b1111 F
1!
#1680000
0!
#1685000
b100 V
1!
#1690000
0!
#1695000
b100000001 (
b100000001 *
b100000001 H
b101 V
b100000001 2
b1 P
1!
#1700000
0!
#1705000
b11 '
b11 +
b11 ,
b110 V
1!
#1710000
0!
#1715000
b1111 (
b1111 *
b1111 H
b111 V
1!
#1720000
0!
#1725000
b10000 (
b10000 *
b10000 H
b1 '
b1 +
b1 ,
b0 V
b10000 F
1!
#1730000
0!
#1735000
b1110011 '
b1110011 +
b1110011 ,
b1 V
1!
#1740000
0!
#1745000
b111 1
b11 /
b10 V
b1110011 N
1!
#1750000
0!
#1755000
b10001 (
b10001 *
b10001 H
b1011 V
b10001 F
1!
#1760000
0!
